Workbook

Sheet LIASSES MULTI APPARTEMENT
A1: LIASSES FISCALES MULTI APPARTEMENTS
A4: Année Fiscale | B4: =YEAR(TODAY())-1 -> 2025 | D4: Espace Pro : impot gouv : Déclarer : Résultat
A6: Compte de resultat
A8: Année | B8: =B4 -> 2025 | D8: Année | E8: =B4+1 -> 2026
A9: Dotation aux ammortissements (année en cours) | B9: ='Appartement 1'!B83+'Appartement 2'!B83 -> 8325 | D9: Dotation aux ammortissements (année en cours) | E9: ='Appartement 1'!E83+'Appartement 2'!E83 -> 8325
A10: Loyer | B10: ='Appartement 1'!B84+'Appartement 2'!B84 -> 16000 | D10: Loyer | E10: ='Appartement 1'!E84+'Appartement 2'!E84 -> 16000
A11: Charges | B11: ='Appartement 1'!B85+'Appartement 2'!B85 -> 20400 | D11: Charges | E11: ='Appartement 1'!E85+'Appartement 2'!E85 -> 2400
A12: Taxes | B12: ='Appartement 1'!B86+'Appartement 2'!B86 -> 0 | D12: Taxes | E12: ='Appartement 1'!E86+'Appartement 2'!E86 -> 0
A13: Interets d'emprunts | B13: ='Appartement 1'!B87+'Appartement 2'!B87 -> 6000 | D13: Interets d'emprunts | E13: ='Appartement 1'!E87+'Appartement 2'!E87 -> 6000
A14: Resultat comptable avant dotation aux amortissements | B14: =B10-B11-B12-B13 -> -10400 | D14: Resultat comptable avant dotation aux amortissements | E14: =E10-E11-E12-E13 -> 7600
A15: Déficits reportables (Nouvellement crée) | B15: =IF(B14<0,-B14,0) -> 10400 | D15: Déficits reportables (Nouvellement crée) | E15: =IF(E14<0,-E14,0) -> 0
A16: Resultat comptable après dotation aux amortissements | B16: =B14-B9 -> -18725 | D16: Resultat comptable après dotation aux amortissements | E16: =E14-E9 -> -725
A17: Amortissement excédentaires (Nouvellement crée) | B17: =MIN(B9 , MAX(0 , B9 - B14)) -> 8325 | C17: =max(0-B16-B15) -> 8325 | D17: Amortissement excédentaires | E17: =MIN(E9 , MAX(0 , E9 - E14)) -> 725
A18: Résultat après imputation des amortissements excédentaires | B18: =B17+B16 -> -10400 | D18: Résultat après imputation des amortissements excédentaires | E18: =E17+E16 -> 0
A19: Amortissement excédentaires ANTERIEURS | B19: ='Appartement 1'!B93+'Appartement 2'!B933 -> 0 | D19: Amortissement excédentaires ANTERIEURS | E19: =B22 -> 8325
A20: Amortissement ANTERIEURS imputés | B20: =IF(B16<=0,0,MIN(B16,B19)) -> 0 | D20: Amortissement ANTERIEURS imputés | E20: =IF(E16<=0,0,MIN(E16,E19)) -> 0
A21: Amortissement ANTERIEURS restants | B21: =B19-B20 -> 0 | D21: Amortissement ANTERIEURS restants | E21: =E19-E20 -> 8325
A22: Amortissements restants à reporter pour les années ultérieures | B22: =B21+B17 -> 8325 | D22: Amortissements restants à reporter pour les années ultérieures | E22: =E21+E17 -> 9050
A23: Résultat après imputation des amortisseùents excédentaires ANTERIEURS | B23: =B18-B20 -> -10400 | D23: Résultat après imputation des amortisseùents excédentaires ANTERIEURS | E23: =E18-E20 -> 0
A24: Déficits ANTERIEURS | B24: 0 | D24: Déficits ANTERIEURS | E24: =B27 -> 10400
A25: Déficits ANTERIEURS imputés | B25: =IF(B23<=0,0,MIN(B23,B24)) -> 0 | D25: Déficits ANTERIEURS imputés | E25: =IF(E23<=0,0,MIN(E23,E24)) -> 0
A26: Déficits ANTERIEURS restants | B26: =B24+B25 -> 0 | D26: Déficits ANTERIEURS restants | E26: =E24+E25 -> 10400
A27: Déficits restants à reportrer pour les années ultérieures | B27: =B26+B15 -> 10400 | D27: Déficits restants à reportrer pour les années ultérieures | E27: =E26+E15 -> 10400
A28: Resultat fiscal après imputation : 1/ amortissements excedentaires de l'année en cours 2/ amortissement excédentaires antérieurs 3/ déficits antérieurs | B28: =B23-B25 -> -10400 | D28: Resultat fiscal après imputation : 1/ amortissements excedentaires de l'année en cours 2/ amortissement excédentaires antérieurs 3/ déficits antérieurs | E28: =E23-E25 -> 0
A29: Disponibilité Antérieurs | B29: 0 | D29: Disponibilité Antérieurs | E29: =B30 -> 0
A30: Disponibilités | B30: =Max(0,B10-B11-B12-B13)+B29 -> 0 | D30: Disponibilités | E30: =Max(0,E10-E11-E12-E13)+E29 -> 7600
A33: BILAN (2033-A)
A34: Année | B34: =B4 -> 2025 | I34: Année | J34: =B4+1 -> 2026
B35: ACTIF | C35: BRUT | E35: Amortissement/provisions | G35: Net Exercice N | J35: ACTIF | K35: BRUT | M35: Amortissement/provisions | O35: Net Exercice N
A36: Actif immobilisé | B36: Immobilisation corporelles | C36: "028" | D36: ='Appartement 1'!D110+'Appartement 2'!D108 -> 300000 | E36: "030" | F36: ='Appartement 1'!F110+'Appartement 2'!F108 -> 8325 | G36: =D36-F36 -> 291675 | I36: Actif immobilisé | J36: Immobilisation corporelles | K36: "028" | L36: =D36 -> 300000 | M36: "030" | N36: ='Appartement 1'!N110+'Appartement 2'!N108 -> 16650 | O36: =L36-N36 -> 283350
B37: Immobilisation financière | C37: "040" | D37: 0 | E37: "042" | F37: 0 | G37: 0 | J37: Immobilisation financière | K37: "040" | L37: 0 | M37: "042" | N37: 0 | O37: 0
B38: Total | C38: "044" | D38: =D36+D37 -> 300000 | E38: "048" | F38: =F36+F37 -> 8325 | G38: =G36+G37 -> 291675 | J38: Total | K38: "044" | L38: =L36+L37 -> 300000 | M38: "048" | N38: =N36+N37 -> 16650 | O38: =O36+O37 -> 283350
A39: Actif Circulant | I39: Actif Circulant
B40: Disponibilités | C40: "084" | D40: =B30 -> 0 | G40: =D40 -> 0 | J40: Disponibilités | K40: "084" | L40: =J30 | O40: =L40
A42: Total | C42: "110" | D42: =D38+D40 -> 300000 | E42: "112" | F42: =F38 -> 8325 | G42: =G38+G40 -> 291675 | I42: Total | K42: "110" | L42: =L38+L40 -> 300000 | M42: "112" | N42: =N38 -> 16650 | O42: =O38+O40 -> 283350
B43: PASSIF | G43: Net Exercice N | J43: PASSIF | O43: Net Exercice N
B44: Capital social ou individuel | C44: "120" | G44: =G42-G46-G48 -> 134400 | J44: Capital social ou individuel | K44: "120" | O44: =O42-O46-O48 -> 124575
B46: Resultat de l'exercice | C46: "136" | G46: =B16 -> -18725 | J46: Resultat de l'exercice | K46: "136" | O46: =E16 -> -725
B48: Emrpunt et dettes assimilés | C48: "156" | G48: ='Appartement 1'!G122 +'Appartement 2'!G120 -> 176000 | J48: Emrpunt et dettes assimilés | K48: "156" | O48: ='Appartement 1'!O122+'Appartement 2'!O120 -> 159500
B49: Total II | C49: "176" | G49: =G48 -> 176000 | J49: Total II | K49: "176" | O49: =O48 -> 159500
B50: Total III | C50: "180" | G50: =SUM(G44:G48) -> 291675 | J50: Total III | K50: "180" | O50: =SUM(O44:O48) -> 283350
A52: 2033-B | E52: Equilibre | F52: =IF(((B14 - B9) + C67)=B28,"C'est bon","C'est pas bon") -> C'est bon | J52: Equilibre | K52: =IF(((E14 - E9) + I67)=E28,"C'est bon","C'est pas bon") -> C'est bon
B53: =B4 -> 2025 | H53: =B4+1 -> 2026
A54: A- RESULTAT COMPTABLE | G54: A- RESULTAT COMPTABLE
A55: production vendue : services | B55: "218" | C55: =B10 -> 16000 | G55: production vendue : services | H55: "218" | I55: =E10 -> 16000
A56: Total produit d'exploitation | B56: "232" | C56: =C55 -> 16000 | G56: Total produit d'exploitation | H56: "232" | I56: =I55 -> 16000
A57: Autre charges externes | B57: "242" | C57: =B11 -> 20400 | G57: Autre charges externes | H57: "242" | I57: =E11 -> 2400
A58: Impots taxe et versement assimilés | B58: "244" | C58: =B12 -> 0 | G58: Impots taxe et versement assimilés | H58: "244" | I58: =E12 -> 0
A59: Dotations aux amortissements | B59: "254" | C59: =B9 -> 8325 | G59: Dotations aux amortissements | H59: "254" | I59: =E9 -> 8325
A60: Total charges d'exploitation | B60: "264" | C60: =SUM(C57:C59) -> 28725 | G60: Total charges d'exploitation | H60: "264" | I60: =SUM(I57:I59) -> 10725
A61: Resultat d'exploitation | B61: "270" | C61: =C56-C60 -> -12725 | G61: Resultat d'exploitation | H61: "270" | I61: =I56-I60 -> 5275
A62: Charges financières | B62: "294" | C62: =B13 -> 6000 | G62: Charges financières | H62: "294" | I62: =E13 -> 6000
A63: Benefices ou perte | B63: "310" | C63: =B16 -> -18725 | G63: Benefices ou perte | H63: "310" | I63: =E16 -> -725
A64: B- RESULTAT FISCAL | G64: B- RESULTAT FISCAL
A65: Reporter les benef compables | B65: "312" | C65: =Max(0,C63) -> 0 | D65: "314" | E65: =-MIN(0,C63) -> 18725 | G65: Reporter les benef compables | H65: "312" | I65: =Max(0,I63) -> 0 | J65: "314" | K65: =-MIN(0,I63) -> 725
A66: Amortissements excedentaires | B66: "318" | C66: =B17 -> 8325 | D66: "342" | E66: =IF(B14 > 0 , MIN(B14 , B9) , 0) -> 0 | G66: Amortissements excedentaires | H66: "318" | I66: =E17 -> 725 | J66: "342" | K66: =IF(E14 > 0 , MIN(E14 , E9) , 0) -> 7600
A67: En ligne : deduction de l'execice : deduction diverses Papier : creance du au titre du report en arrière du deficit | B67: "350" | C67: =B17 -> 8325 | D67: "360" | E67: =IF(B14 < 0 , ABS(B14) , 0) -> 10400 | G67: En ligne : deduction de l'execice : deduction diverses Papier : creance du au titre du report en arrière du deficit | H67: "350" | I67: =E17 -> 725 | J67: "360" | K67: =IF(E14 < 0 , ABS(E14) , 0) -> 0
A68: Resultat Fiscal avant imputation | B68: "352" | C68: =IF(B23>0,B23,0) -> 0 | D68: "354" | E68: =IF(B23<0,-B23,0) -> 10400 | G68: Resultat Fiscal avant imputation | H68: "352" | I68: =IF(E23>0,E23,0) -> 0 | J68: "354" | K68: =IF(E23<0,-E23,0) -> 0
A69: Resultat Fiscal apres imputation | B69: "370" | C69: =MAX(0 , B14 - B9) -> 0 | D69: "372" | E69: =IF(B28<0,-B28,0) -> 10400 | G69: Resultat Fiscal | H69: "370" | I69: =MAX(0 , E14 - E9) -> 0 | J69: "372" | K69: =IF(E28<0,-E28,0) -> 0
A71: 2033-C
A72: 1- Immobilisations
A74: Année | B74: =B4 -> 2025 | K74: Année | L74: =B4+1 -> 2026
B76: Valeur brut des immo en début d'exercice | D76: Augmentation | F76: Diminution | H76: Valeur brute des immo à la fin de l'exercice | L76: Valeur brut des immo en début d'exercice | N76: Augmentation | P76: Diminution | R76: Valeur brute des immo à la fin de l'exercice
A77: Terrains | B77: "420" | C77: 0 | D77: "422" | E77: ='Appartement 1'!E152+'Appartement 2'!E153 -> 45000 | F77: "424" | G77: 0 | H77: "426" | I77: =C77+E77+G77 -> 45000 | K77: Terrains | L77: "420" | M77: =I77 -> 45000 | N77: "422" | O77: 0 | P77: "424" | Q77: 0 | R77: "426" | S77: =M77+O77+Q77 -> 45000
A78: Constructions | B78: "430" | C78: 0 | D78: "432" | E78: ='Appartement 1'!E153+'Appartement 2'!E154 -> 165000 | F78: "434" | G78: 0 | H78: "436" | I78: =C78+E78+G78 -> 165000 | K78: Constructions | L78: "430" | M78: =I78 -> 165000 | N78: "432" | O78: 0 | P78: "434" | Q78: 0 | R78: "436" | S78: =M78+O78+Q78 -> 165000
A79: Installations techniques materiel et outillage | B79: "440" | C79: 0 | D79: "442" | E79: ='Appartement 1'!E154+'Appartement 2'!E155 -> 45000 | F79: "444" | G79: 0 | H79: "446" | I79: =C79+E79+G79 -> 45000 | K79: Installations techniques materiel et outillage | L79: "440" | M79: =I79 -> 45000 | N79: "442" | O79: 0 | P79: "444" | Q79: 0 | R79: "446" | S79: =M79+O79+Q79 -> 45000
A80: Installations générales agencement divers | B80: "450" | C80: 0 | D80: "452" | E80: ='Appartement 1'!E155+'Appartement 2'!E156 -> 45000 | F80: "454" | G80: 0 | H80: "456" | I80: =C80+E80+G80 -> 45000 | K80: Installations générales agencement divers | L80: "450" | M80: =I80 -> 45000 | N80: "452" | O80: 0 | P80: "454" | Q80: 0 | R80: "456" | S80: =M80+O80+Q80 -> 45000
A81: Autres immobilisations corporelles | B81: "470" | C81: 0 | D81: "472" | E81: ='Appartement 1'!E156+'Appartement 2'!E157 -> 0 | F81: "474" | G81: 0 | H81: "476" | I81: =C81+E81+G81 -> 0 | K81: Autres immobilisations corporelles | L81: "470" | M81: =I81 -> 0 | N81: "472" | O81: 0 | P81: "474" | Q81: 0 | R81: "476" | S81: =M81+O81+Q81 -> 0
A82: Immobilisations financières | B82: "480" | C82: 0 | D82: "482" | E82: ='Appartement 1'!E157+'Appartement 2'!E158 -> 0 | F82: "484" | G82: 0 | H82: "486" | I82: =C82+E82+G82 -> 0 | K82: Immobilisations financières | L82: "480" | M82: 0 | N82: "482" | O82: 0 | P82: "484" | Q82: 0 | R82: "486" | S82: =M82+O82+Q82 -> 0
A83: Total | B83: "490" | C83: 0 | D83: "492" | E83: =SUM(E77:E82) -> 300000 | F83: "494" | G83: 0 | H83: "496" | I83: =SUM(I77:I82) -> 300000 | K83: Total | L83: "490" | M83: =SUM(M77:M82) -> 300000 | N83: "492" | O83: 0 | P83: "494" | Q83: 0 | R83: "496" | S83: =SUM(S77:S82) -> 300000
A85: 2 - AMMORTISSEMENT
B86: =B4 -> 2025 | L86: =B4+1 -> 2026
B87: Amortissements en début d'exercice | D87: Augmentation (dotation exercice) | F87: Diminution | H87: Valeur brute des immo à la fin de l'exercice | L87: Amortissements en début d'exercice | N87: Augmentation (dotation exercice) | P87: Diminution | R87: Valeur brute des immo à la fin de l'exercice
A88: Immobilisations incorporelless | B88: "500" | C88: 0 | D88: "502" | E88: 0 | F88: "504" | G88: 0 | H88: "506" | I88: =C88+E88+G88 -> 0 | K88: Immobilisations incorporelless | L88: "500" | M88: =I88 -> 0 | N88: "502" | O88: 0 | P88: "504" | Q88: 0 | R88: "506" | S88: =M88+O88+Q88 -> 0
A89: Terrains | B89: "510" | C89: 0 | D89: "512" | E89: 0 | F89: "514" | G89: 0 | H89: "516" | I89: =C89+E89+G89 -> 0 | K89: Terrains | L89: "510" | M89: =I89 -> 0 | N89: "512" | O89: 0 | P89: "514" | Q89: 0 | R89: "516" | S89: =M89+O89+Q89 -> 0
A90: Constructions | B90: "520" | C90: 0 | D90: "522" | E90: ='Appartement 1'!E165+'Appartement 2'!E166 -> 3525 | F90: "524" | G90: 0 | H90: "526" | I90: =C90+E90+G90 -> 3525 | K90: Constructions | L90: "520" | M90: =I90 -> 3525 | N90: "522" | O90: ='Appartement 1'!O165+'Appartement 2'!O166 -> 3525 | P90: "524" | Q90: 0 | R90: "526" | S90: =M90+O90+Q90 -> 7050
A91: Installations techniques materiel et outillage | B91: "530" | C91: 0 | D91: "532" | E91: ='Appartement 1'!E166+'Appartement 2'!E167 -> 1800 | F91: "534" | G91: 0 | H91: "536" | I91: =C91+E91+G91 -> 1800 | K91: Installations techniques materiel et outillage | L91: "530" | M91: =I91 -> 1800 | N91: "532" | O91: ='Appartement 1'!O166+'Appartement 2'!O167 -> 1800 | P91: "534" | Q91: 0 | R91: "536" | S91: =M91+O91+Q91 -> 3600
A92: Installations générales agencement divers | B92: "540" | C92: 0 | D92: "542" | E92: ='Appartement 1'!E167+'Appartement 2'!E168 -> 3000 | F92: "544" | G92: 0 | H92: "546" | I92: =C92+E92+G92 -> 3000 | K92: Installations générales agencement divers | L92: "540" | M92: =I92 -> 3000 | N92: "542" | O92: ='Appartement 1'!O167+'Appartement 2'!O168 -> 3000 | P92: "544" | Q92: 0 | R92: "546" | S92: =M92+O92+Q92 -> 6000
A93: Autres immobilisations corporelles | B93: "560" | C93: 0 | D93: "562" | E93: ='Appartement 1'!E168+'Appartement 2'!E169 -> 0 | F93: "564" | G93: 0 | H93: "566" | I93: =C93+E93+G93 -> 0 | K93: Autres immobilisations corporelles | L93: "560" | M93: =I93 -> 0 | N93: "562" | O93: ='Appartement 1'!O168+'Appartement 2'!O169 -> 0 | P93: "564" | Q93: 0 | R93: "566" | S93: =M93+O93+Q93 -> 0
A94: Total | B94: "570" | C94: 0 | D94: "572" | E94: ='Appartement 1'!E169+'Appartement 2'!E170 -> 8325 | F94: "574" | G94: 0 | H94: "576" | I94: =SUM(I88:I93) -> 8325 | K94: Total | L94: "570" | M94: =SUM(M88:M93) -> 8325 | N94: "572" | O94: =SUM(O88:O93) -> 8325 | P94: "574" | Q94: 0 | R94: "576" | S94: =SUM(S88:S93) -> 16650
A97: 2033-D
A99: Les déficits reportables
A101: Année | B101: =B4 -> 2025 | E101: Année | F101: =B4+1 -> 2026
A103: Déficit restant à reporter au titre de l'exercice précedent | B103: "982" | C103: =B24 -> 0 | E103: Déficit restant à reporter au titre de l'exercice précedent | F103: "982" | G103: =E24 -> 10400
A104: Déficit imputé | B104: "983" | C104: =B25 -> 0 | E104: Déficit imputé | F104: "983" | G104: =E25 -> 0
A105: Déficit reportable | B105: "984" | C105: =C103-C104 -> 0 | E105: Déficit reportable | F105: "984" | G105: =G103-G104 -> 10400
A106: Déficit de l'exercice | B106: "860" | C106: =B15 -> 10400 | E106: Déficit de l'exercice | F106: "860" | G106: =E15 -> 0
A107: Total des déficits restants à reporter | B107: "870" | C107: =C105+C106 -> 10400 | E107: Total des déficits restants à reporter | F107: "870" | G107: =G105+G106 -> 10400

Sheet Appartement 1
A1: Etape 1 prix de départ Appartement 1: | D1: Espace Pro : impot gouv : Déclarer : Résultat
A4: Prix d'achat | B4: 150000
A5: Frais de notaire | B5: =0 -> 0
A6: frais d'agence | B6: =0 -> 0
A7: Mobilier | B7: =0 -> 0
A8: Travaux à amortir | B8: =0 -> 0
A9: Base amortissable | B9: =IF(B4>0,SUM(B4:B6),IF(E4>0,E4,0)) -> 150000
A11: Etape 2 : Décomposition et amortissement
A12: Date de début d'activité | B12: 45658
A13: Année de début d'activité | B13: =YEAR(B12) -> 2025 | E13: Année d'exercice | F13: =YEAR(TODAY())-1 -> 2025 | H13: =F13-B13+26 -> 26
A14: Prorata | B14: =YEARFRAC(B12,DATE(YEAR(B12)+1,1,1),4) -> 1 | AD14: Travaux/Mobilier | AE14: Montant | AF14: Date debut | AG14: Nbr année amortissement | AH14: Prorata première année
A15: Terrain | B15: =15% -> 0.15 | AD15: Travaux/Mobilier 1 | AE15: 0 | AF15: 45809 | AG15: 10 | AH15: =YEARFRAC(AF15,DATE(YEAR(AF15)+1,1,1),4) -> 0.58333333
A16: Structure (Gros oeuvre) | B16: =40% -> 0.4 | C16: du total sur | D16: 50 | E16: ans | AD16: Travaux/Mobilier 2 | AE16: 0 | AF16: 46174 | AG16: 10 | AH16: =YEARFRAC(AF16,DATE(YEAR(AF16)+1,1,1),4) -> 0.58333333
A17: Façade, étanchieté | B17: =15% -> 0.15 | C17: du total sur | D17: 40 | E17: ans | AD17: Travaux/Mobilier 3 | AE17: 0 | AF17: 46539 | AG17: 10 | AH17: =YEARFRAC(AF17,DATE(YEAR(AF17)+1,1,1),4) -> 0.58333333
A18: IGT, Equipement | B18: =15% -> 0.15 | C18: du total sur | D18: 25 | E18: ans | AD18: Travaux/Mobilier 4 | AE18: 0 | AF18: 46905 | AG18: 10 | AH18: =YEARFRAC(AF18,DATE(YEAR(AF18)+1,1,1),4) -> 0.58333333
A19: Agencements (cloisons, chapes, platerie, revetement, plomberie, cablage) | B19: =15% -> 0.15 | C19: du total sur | D19: 15 | E19: ans | AD19: Travaux/Mobilier 5 | AE19: 0 | AF19: 47270 | AG19: 10 | AH19: =YEARFRAC(AF19,DATE(YEAR(AF19)+1,1,1),4) -> 0.58333333
A20: Mobilier+travaux avant 1ere location | B20: =B7+B8 -> 0 | D20: 10 | E20: ans | AD20: Travaux/Mobilier 6 | AE20: 0 | AF20: 47635 | AG20: 10 | AH20: =YEARFRAC(AF20,DATE(YEAR(AF20)+1,1,1),4) -> 0.58333333
A21: Frais de notaire | B21: =B5 -> 0 | D21: 0 | AD21: Travaux/Mobilier 7 | AE21: 0 | AF21: 48000 | AG21: 10 | AH21: =YEARFRAC(AF21,DATE(YEAR(AF21)+1,1,1),4) -> 0.58333333
A22: Frais d'agence | B22: =B6 -> 0 | D22: 0 | AD22: Travaux/Mobilier 8 | AE22: 0 | AF22: 48000 | AG22: 10 | AH22: =YEARFRAC(AF22,DATE(YEAR(AF22)+1,1,1),4) -> 0.58333333
AD23: Travaux/Mobilier 9 | AE23: 0 | AF23: 48000 | AG23: 10 | AH23: =YEARFRAC(AF23,DATE(YEAR(AF23)+1,1,1),4) -> 0.58333333
C24: Augmentation Amortissement (dotations) | K24: Immobilisations net | Q24: Ammortissement début d'excercice | W24: Ammortissement fin exercice | AD24: Travaux/Mobilier 10 | AE24: 0 | AF24: 48000 | AG24: 10 | AH24: =YEARFRAC(AF24,DATE(YEAR(AF24)+1,1,1),4) -> 0.58333333
A25: Année | B25: Structure | C25: Façade | D25: Equipement | E25: Agencement | F25: Autres immobilisations corporelles | G25: Total Ammortissement | H25: Construction | I25: Construction | J25: Immo equipement | K25: Immo agencement | L25: Autres immobilisations corporelles | N25: Terrain | O25: Total | P25: Construction | Q25: Terrain | R25: Equipement | S25: Agencement | T25: Autres immobilisations corporelles | U25: Total | V25: Construction | W25: Terrain | X25: Equipement | Y25: Agencement | Z25: Autres immobilisations corporelles | AB25: Total
A26: 2025 | B26: =IF(A26<$B$13+$D$16,$B$16*$B$9/$D$16,0)*B14 -> 1200 | C26: =IF(A26<$B$13+$D17,$B$17*$B$9/$D$17,0)*B14 -> 562.5 | D26: =IF(A26<$B$13+$D18,$B$18*$B$9/$D$18,0)*B14 -> 900 | E26: =IF(A26<$B$13+$D$19,$B$19*$B$9/$D$19,0)*B14 -> 1500 | F26: =(IF(A26<$B$13+$D$20,$B$20/$D$20,0)*B14) -> 0 | G26: =SUM(B26:F26) -> 4162.5 | H26: =B26+C26 -> 1762.5 | I26: =$B$9*($B$16+$B$17)-V26 -> 80737.5 | J26: =$B$9*($B$18)-X26 -> 21600 | K26: =$B$9*($B$19)-Y26 -> 21000 | L26: =$B$20-Z26+AJ26 -> 0 | N26: =$B$9*$B$15 -> 22500 | O26: =SUM(I26:N26) -> 145837.5 | P26: 0 | Q26: 0 | R26: 0 | S26: 0 | T26: 0 | U26: 0 | V26: =P26+H26 -> 1762.5 | W26: 0 | X26: =R26+D26 -> 900 | Y26: =S26+E26 -> 1500 | Z26: =T26+F26 -> 0 | AB26: =SUM(V26:AA26) -> 4162.5
A27: 2026 | B27: =IF(A27=$B$13+$D$16,($B$16*$B$9/$D$16)*(1-$B$14),IF(A27<$B$13+$D$16,$B$16*$B$9/$D$16,0)) -> 1200 | C27: =IF(A27=$B$13+$D$17,($B$17*$B$9/$D$17)*(1-$B$14),IF(A27<$B$13+$D$17,$B$17*$B$9/$D$17,0)) -> 562.5 | D27: =IF(A27=$B$13+$D$18,($B$18*$B$9/$D$18)*(1-$B$14),IF(A27<$B$13+$D$18,$B$18*$B$9/$D$18,0)) -> 900 | E27: =IF(A27=$B$13+$D$19,($B$19*$B$9/$D$19)*(1-$B$14),IF(A27<$B$13+$D$19,$B$19*$B$9/$D$19,0)) -> 1500 | F27: =IF(A27=$B$13+$D$20,($B$20/$D$20)*(1-$B$14),IF(A27<$B$13+$D$20,$B$20/$D$20,0)) -> 0 | G27: =SUM(B27:F27) -> 4162.5 | H27: =B27+C27 -> 1762.5 | I27: =$B$9*($B$16+$B$17)-V27 -> 78975 | J27: =$B$9*($B$18)-X27 -> 20700 | K27: =$B$9*($B$19)-Y27 -> 19500 | L27: =$B$20-Z27+AJ27 -> 0 | N27: =$B$9*$B$15 -> 22500 | O27: =SUM(I27:N27) -> 141675 | P27: =V26 -> 1762.5 | Q27: 0 | R27: =X26 -> 900 | S27: =Y26 -> 1500 | T27: =Z26 -> 0 | U27: =AB26 -> 4162.5 | V27: =P27+H27 -> 3525 | W27: 0 | X27: =R27+D27 -> 1800 | Y27: =S27+E27 -> 3000 | Z27: =T27+F27 -> 0 | AB27: =SUM(V27:AA27) -> 8325
A28: =A27+1 -> 2027 | B28: =IF(A28=$B$13+$D$16,($B$16*$B$9/$D$16)*(1-$B$14),IF(A28<$B$13+$D$16,$B$16*$B$9/$D$16,0)) -> 1200 | C28: =IF(A28=$B$13+$D$17,($B$17*$B$9/$D$17)*(1-$B$14),IF(A28<$B$13+$D$17,$B$17*$B$9/$D$17,0)) -> 562.5 | D28: =IF(A28=$B$13+$D$18,($B$18*$B$9/$D$18)*(1-$B$14),IF(A28<$B$13+$D$18,$B$18*$B$9/$D$18,0)) -> 900 | E28: =IF(A28=$B$13+$D$19,($B$19*$B$9/$D$19)*(1-$B$14),IF(A28<$B$13+$D$19,$B$19*$B$9/$D$19,0)) -> 1500 | F28: =IF(A28=$B$13+$D$20,($B$20/$D$20)*(1-$B$14),IF(A28<$B$13+$D$20,$B$20/$D$20,0)) -> 0 | G28: =SUM(B28:F28) -> 4162.5 | H28: =B28+C28 -> 1762.5 | I28: =$B$9*($B$16+$B$17)-V28 -> 77212.5 | J28: =$B$9*($B$18)-X28 -> 19800 | K28: =$B$9*($B$19)-Y28 -> 18000 | L28: =$B$20-Z28+AJ28 -> 0 | N28: =$B$9*$B$15 -> 22500 | O28: =SUM(I28:N28) -> 137512.5 | P28: =V27 -> 3525 | Q28: 0 | R28: =X27 -> 1800 | S28: =Y27 -> 3000 | T28: =Z27 -> 0 | U28: =AB27 -> 8325 | V28: =P28+H28 -> 5287.5 | W28: 0 | X28: =R28+D28 -> 2700 | Y28: =S28+E28 -> 4500 | Z28: =T28+F28 -> 0 | AB28: =SUM(V28:AA28) -> 12487.5
A29: =A28+1 -> 2028 | B29: =IF(A29=$B$13+$D$16,($B$16*$B$9/$D$16)*(1-$B$14),IF(A29<$B$13+$D$16,$B$16*$B$9/$D$16,0)) -> 1200 | C29: =IF(A29=$B$13+$D$17,($B$17*$B$9/$D$17)*(1-$B$14),IF(A29<$B$13+$D$17,$B$17*$B$9/$D$17,0)) -> 562.5 | D29: =IF(A29=$B$13+$D$18,($B$18*$B$9/$D$18)*(1-$B$14),IF(A29<$B$13+$D$18,$B$18*$B$9/$D$18,0)) -> 900 | E29: =IF(A29=$B$13+$D$19,($B$19*$B$9/$D$19)*(1-$B$14),IF(A29<$B$13+$D$19,$B$19*$B$9/$D$19,0)) -> 1500 | F29: =IF(A29=$B$13+$D$20,($B$20/$D$20)*(1-$B$14),IF(A29<$B$13+$D$20,$B$20/$D$20,0)) -> 0 | G29: =SUM(B29:F29) -> 4162.5 | H29: =B29+C29 -> 1762.5 | I29: =$B$9*($B$16+$B$17)-V29 -> 75450 | J29: =$B$9*($B$18)-X29 -> 18900 | K29: =$B$9*($B$19)-Y29 -> 16500 | L29: =$B$20-Z29+AJ29 -> 0 | N29: =$B$9*$B$15 -> 22500 | O29: =SUM(I29:N29) -> 133350 | P29: =V28 -> 5287.5 | Q29: 0 | R29: =X28 -> 2700 | S29: =Y28 -> 4500 | T29: =Z28 -> 0 | U29: =AB28 -> 12487.5 | V29: =P29+H29 -> 7050 | W29: 0 | X29: =R29+D29 -> 3600 | Y29: =S29+E29 -> 6000 | Z29: =T29+F29 -> 0 | AB29: =SUM(V29:AA29) -> 16650
A30: =A29+1 -> 2029 | B30: =IF(A30=$B$13+$D$16,($B$16*$B$9/$D$16)*(1-$B$14),IF(A30<$B$13+$D$16,$B$16*$B$9/$D$16,0)) -> 1200 | C30: =IF(A30=$B$13+$D$17,($B$17*$B$9/$D$17)*(1-$B$14),IF(A30<$B$13+$D$17,$B$17*$B$9/$D$17,0)) -> 562.5 | D30: =IF(A30=$B$13+$D$18,($B$18*$B$9/$D$18)*(1-$B$14),IF(A30<$B$13+$D$18,$B$18*$B$9/$D$18,0)) -> 900 | E30: =IF(A30=$B$13+$D$19,($B$19*$B$9/$D$19)*(1-$B$14),IF(A30<$B$13+$D$19,$B$19*$B$9/$D$19,0)) -> 1500 | F30: =IF(A30=$B$13+$D$20,($B$20/$D$20)*(1-$B$14),IF(A30<$B$13+$D$20,$B$20/$D$20,0)) -> 0 | G30: =SUM(B30:F30) -> 4162.5 | H30: =B30+C30 -> 1762.5 | I30: =$B$9*($B$16+$B$17)-V30 -> 73687.5 | J30: =$B$9*($B$18)-X30 -> 18000 | K30: =$B$9*($B$19)-Y30 -> 15000 | L30: =$B$20-Z30+AJ30 -> 0 | N30: =$B$9*$B$15 -> 22500 | O30: =SUM(I30:N30) -> 129187.5 | P30: =V29 -> 7050 | Q30: 0 | R30: =X29 -> 3600 | S30: =Y29 -> 6000 | T30: =Z29 -> 0 | U30: =AB29 -> 16650 | V30: =P30+H30 -> 8812.5 | W30: 0 | X30: =R30+D30 -> 4500 | Y30: =S30+E30 -> 7500 | Z30: =T30+F30 -> 0 | AB30: =SUM(V30:AA30) -> 20812.5
A31: =A30+1 -> 2030 | B31: =IF(A31=$B$13+$D$16,($B$16*$B$9/$D$16)*(1-$B$14),IF(A31<$B$13+$D$16,$B$16*$B$9/$D$16,0)) -> 1200 | C31: =IF(A31=$B$13+$D$17,($B$17*$B$9/$D$17)*(1-$B$14),IF(A31<$B$13+$D$17,$B$17*$B$9/$D$17,0)) -> 562.5 | D31: =IF(A31=$B$13+$D$18,($B$18*$B$9/$D$18)*(1-$B$14),IF(A31<$B$13+$D$18,$B$18*$B$9/$D$18,0)) -> 900 | E31: =IF(A31=$B$13+$D$19,($B$19*$B$9/$D$19)*(1-$B$14),IF(A31<$B$13+$D$19,$B$19*$B$9/$D$19,0)) -> 1500 | F31: =IF(A31=$B$13+$D$20,($B$20/$D$20)*(1-$B$14),IF(A31<$B$13+$D$20,$B$20/$D$20,0)) -> 0 | G31: =SUM(B31:F31) -> 4162.5 | H31: =B31+C31 -> 1762.5 | I31: =$B$9*($B$16+$B$17)-V31 -> 71925 | J31: =$B$9*($B$18)-X31 -> 17100 | K31: =$B$9*($B$19)-Y31 -> 13500 | L31: =$B$20-Z31+AJ31 -> 0 | N31: =$B$9*$B$15 -> 22500 | O31: =SUM(I31:N31) -> 125025 | P31: =V30 -> 8812.5 | Q31: 0 | R31: =X30 -> 4500 | S31: =Y30 -> 7500 | T31: =Z30 -> 0 | U31: =AB30 -> 20812.5 | V31: =P31+H31 -> 10575 | W31: 0 | X31: =R31+D31 -> 5400 | Y31: =S31+E31 -> 9000 | Z31: =T31+F31 -> 0 | AB31: =SUM(V31:AA31) -> 24975
A32: =A31+1 -> 2031 | B32: =IF(A32=$B$13+$D$16,($B$16*$B$9/$D$16)*(1-$B$14),IF(A32<$B$13+$D$16,$B$16*$B$9/$D$16,0)) -> 1200 | C32: =IF(A32=$B$13+$D$17,($B$17*$B$9/$D$17)*(1-$B$14),IF(A32<$B$13+$D$17,$B$17*$B$9/$D$17,0)) -> 562.5 | D32: =IF(A32=$B$13+$D$18,($B$18*$B$9/$D$18)*(1-$B$14),IF(A32<$B$13+$D$18,$B$18*$B$9/$D$18,0)) -> 900 | E32: =IF(A32=$B$13+$D$19,($B$19*$B$9/$D$19)*(1-$B$14),IF(A32<$B$13+$D$19,$B$19*$B$9/$D$19,0)) -> 1500 | F32: =IF(A32=$B$13+$D$20,($B$20/$D$20)*(1-$B$14),IF(A32<$B$13+$D$20,$B$20/$D$20,0)) -> 0 | G32: =SUM(B32:F32) -> 4162.5 | H32: =B32+C32 -> 1762.5 | I32: =$B$9*($B$16+$B$17)-V32 -> 70162.5 | J32: =$B$9*($B$18)-X32 -> 16200 | K32: =$B$9*($B$19)-Y32 -> 12000 | L32: =$B$20-Z32+AJ32 -> 0 | N32: =$B$9*$B$15 -> 22500 | O32: =SUM(I32:N32) -> 120862.5 | P32: =V31 -> 10575 | Q32: 0 | R32: =X31 -> 5400 | S32: =Y31 -> 9000 | T32: =Z31 -> 0 | U32: =AB31 -> 24975 | V32: =P32+H32 -> 12337.5 | W32: 0 | X32: =R32+D32 -> 6300 | Y32: =S32+E32 -> 10500 | Z32: =T32+F32 -> 0 | AB32: =SUM(V32:AA32) -> 29137.5
A33: =A32+1 -> 2032 | B33: =IF(A33=$B$13+$D$16,($B$16*$B$9/$D$16)*(1-$B$14),IF(A33<$B$13+$D$16,$B$16*$B$9/$D$16,0)) -> 1200 | C33: =IF(A33=$B$13+$D$17,($B$17*$B$9/$D$17)*(1-$B$14),IF(A33<$B$13+$D$17,$B$17*$B$9/$D$17,0)) -> 562.5 | D33: =IF(A33=$B$13+$D$18,($B$18*$B$9/$D$18)*(1-$B$14),IF(A33<$B$13+$D$18,$B$18*$B$9/$D$18,0)) -> 900 | E33: =IF(A33=$B$13+$D$19,($B$19*$B$9/$D$19)*(1-$B$14),IF(A33<$B$13+$D$19,$B$19*$B$9/$D$19,0)) -> 1500 | F33: =IF(A33=$B$13+$D$20,($B$20/$D$20)*(1-$B$14),IF(A33<$B$13+$D$20,$B$20/$D$20,0)) -> 0 | G33: =SUM(B33:F33) -> 4162.5 | H33: =B33+C33 -> 1762.5 | I33: =$B$9*($B$16+$B$17)-V33 -> 68400 | J33: =$B$9*($B$18)-X33 -> 15300 | K33: =$B$9*($B$19)-Y33 -> 10500 | L33: =$B$20-Z33+AJ33 -> 0 | N33: =$B$9*$B$15 -> 22500 | O33: =SUM(I33:N33) -> 116700 | P33: =V32 -> 12337.5 | Q33: 0 | R33: =X32 -> 6300 | S33: =Y32 -> 10500 | T33: =Z32 -> 0 | U33: =AB32 -> 29137.5 | V33: =P33+H33 -> 14100 | W33: 0 | X33: =R33+D33 -> 7200 | Y33: =S33+E33 -> 12000 | Z33: =T33+F33 -> 0 | AB33: =SUM(V33:AA33) -> 33300
A34: =A33+1 -> 2033 | B34: =IF(A34=$B$13+$D$16,($B$16*$B$9/$D$16)*(1-$B$14),IF(A34<$B$13+$D$16,$B$16*$B$9/$D$16,0)) -> 1200 | C34: =IF(A34=$B$13+$D$17,($B$17*$B$9/$D$17)*(1-$B$14),IF(A34<$B$13+$D$17,$B$17*$B$9/$D$17,0)) -> 562.5 | D34: =IF(A34=$B$13+$D$18,($B$18*$B$9/$D$18)*(1-$B$14),IF(A34<$B$13+$D$18,$B$18*$B$9/$D$18,0)) -> 900 | E34: =IF(A34=$B$13+$D$19,($B$19*$B$9/$D$19)*(1-$B$14),IF(A34<$B$13+$D$19,$B$19*$B$9/$D$19,0)) -> 1500 | F34: =IF(A34=$B$13+$D$20,($B$20/$D$20)*(1-$B$14),IF(A34<$B$13+$D$20,$B$20/$D$20,0)) -> 0 | G34: =SUM(B34:F34) -> 4162.5 | H34: =B34+C34 -> 1762.5 | I34: =$B$9*($B$16+$B$17)-V34 -> 66637.5 | J34: =$B$9*($B$18)-X34 -> 14400 | K34: =$B$9*($B$19)-Y34 -> 9000 | L34: =$B$20-Z34+AJ34 -> 0 | N34: =$B$9*$B$15 -> 22500 | O34: =SUM(I34:N34) -> 112537.5 | P34: =V33 -> 14100 | Q34: 0 | R34: =X33 -> 7200 | S34: =Y33 -> 12000 | T34: =Z33 -> 0 | U34: =AB33 -> 33300 | V34: =P34+H34 -> 15862.5 | W34: 0 | X34: =R34+D34 -> 8100 | Y34: =S34+E34 -> 13500 | Z34: =T34+F34 -> 0 | AB34: =SUM(V34:AA34) -> 37462.5
A35: =A34+1 -> 2034 | B35: =IF(A35=$B$13+$D$16,($B$16*$B$9/$D$16)*(1-$B$14),IF(A35<$B$13+$D$16,$B$16*$B$9/$D$16,0)) -> 1200 | C35: =IF(A35=$B$13+$D$17,($B$17*$B$9/$D$17)*(1-$B$14),IF(A35<$B$13+$D$17,$B$17*$B$9/$D$17,0)) -> 562.5 | D35: =IF(A35=$B$13+$D$18,($B$18*$B$9/$D$18)*(1-$B$14),IF(A35<$B$13+$D$18,$B$18*$B$9/$D$18,0)) -> 900 | E35: =IF(A35=$B$13+$D$19,($B$19*$B$9/$D$19)*(1-$B$14),IF(A35<$B$13+$D$19,$B$19*$B$9/$D$19,0)) -> 1500 | F35: =IF(A35=$B$13+$D$20,($B$20/$D$20)*(1-$B$14),IF(A35<$B$13+$D$20,$B$20/$D$20,0)) -> 0 | G35: =SUM(B35:F35) -> 4162.5 | H35: =B35+C35 -> 1762.5 | I35: =$B$9*($B$16+$B$17)-V35 -> 64875 | J35: =$B$9*($B$18)-X35 -> 13500 | K35: =$B$9*($B$19)-Y35 -> 7500 | L35: =$B$20-Z35+AJ35 -> 0 | N35: =$B$9*$B$15 -> 22500 | O35: =SUM(I35:N35) -> 108375 | P35: =V34 -> 15862.5 | Q35: 0 | R35: =X34 -> 8100 | S35: =Y34 -> 13500 | T35: =Z34 -> 0 | U35: =AB34 -> 37462.5 | V35: =P35+H35 -> 17625 | W35: 0 | X35: =R35+D35 -> 9000 | Y35: =S35+E35 -> 15000 | Z35: =T35+F35 -> 0 | AB35: =SUM(V35:AA35) -> 41625
A36: =A35+1 -> 2035 | B36: =IF(A36=$B$13+$D$16,($B$16*$B$9/$D$16)*(1-$B$14),IF(A36<$B$13+$D$16,$B$16*$B$9/$D$16,0)) -> 1200 | C36: =IF(A36=$B$13+$D$17,($B$17*$B$9/$D$17)*(1-$B$14),IF(A36<$B$13+$D$17,$B$17*$B$9/$D$17,0)) -> 562.5 | D36: =IF(A36=$B$13+$D$18,($B$18*$B$9/$D$18)*(1-$B$14),IF(A36<$B$13+$D$18,$B$18*$B$9/$D$18,0)) -> 900 | E36: =IF(A36=$B$13+$D$19,($B$19*$B$9/$D$19)*(1-$B$14),IF(A36<$B$13+$D$19,$B$19*$B$9/$D$19,0)) -> 1500 | F36: =IF(A36=$B$13+$D$20,($B$20/$D$20)*(1-$B$14),IF(A36<$B$13+$D$20,$B$20/$D$20,0)) -> 0 | G36: =SUM(B36:F36) -> 4162.5 | H36: =B36+C36 -> 1762.5 | I36: =$B$9*($B$16+$B$17)-V36 -> 63112.5 | J36: =$B$9*($B$18)-X36 -> 12600 | K36: =$B$9*($B$19)-Y36 -> 6000 | L36: =$B$20-Z36+AJ36 -> 0 | N36: =$B$9*$B$15 -> 22500 | O36: =SUM(I36:N36) -> 104212.5 | P36: =V35 -> 17625 | Q36: 0 | R36: =X35 -> 9000 | S36: =Y35 -> 15000 | T36: =Z35 -> 0 | U36: =AB35 -> 41625 | V36: =P36+H36 -> 19387.5 | W36: 0 | X36: =R36+D36 -> 9900 | Y36: =S36+E36 -> 16500 | Z36: =T36+F36 -> 0 | AB36: =SUM(V36:AA36) -> 45787.5
A37: =A36+1 -> 2036 | B37: =IF(A37=$B$13+$D$16,($B$16*$B$9/$D$16)*(1-$B$14),IF(A37<$B$13+$D$16,$B$16*$B$9/$D$16,0)) -> 1200 | C37: =IF(A37=$B$13+$D$17,($B$17*$B$9/$D$17)*(1-$B$14),IF(A37<$B$13+$D$17,$B$17*$B$9/$D$17,0)) -> 562.5 | D37: =IF(A37=$B$13+$D$18,($B$18*$B$9/$D$18)*(1-$B$14),IF(A37<$B$13+$D$18,$B$18*$B$9/$D$18,0)) -> 900 | E37: =IF(A37=$B$13+$D$19,($B$19*$B$9/$D$19)*(1-$B$14),IF(A37<$B$13+$D$19,$B$19*$B$9/$D$19,0)) -> 1500 | F37: =IF(A37=$B$13+$D$20,($B$20/$D$20)*(1-$B$14),IF(A37<$B$13+$D$20,$B$20/$D$20,0)) -> 0 | G37: =SUM(B37:F37) -> 4162.5 | H37: =B37+C37 -> 1762.5 | I37: =$B$9*($B$16+$B$17)-V37 -> 61350 | J37: =$B$9*($B$18)-X37 -> 11700 | K37: =$B$9*($B$19)-Y37 -> 4500 | L37: =$B$20-Z37+AJ37 -> 0 | N37: =$B$9*$B$15 -> 22500 | O37: =SUM(I37:N37) -> 100050 | P37: =V36 -> 19387.5 | Q37: 0 | R37: =X36 -> 9900 | S37: =Y36 -> 16500 | T37: =Z36 -> 0 | U37: =AB36 -> 45787.5 | V37: =P37+H37 -> 21150 | W37: 0 | X37: =R37+D37 -> 10800 | Y37: =S37+E37 -> 18000 | Z37: =T37+F37 -> 0 | AB37: =SUM(V37:AA37) -> 49950
A38: =A37+1 -> 2037 | B38: =IF(A38=$B$13+$D$16,($B$16*$B$9/$D$16)*(1-$B$14),IF(A38<$B$13+$D$16,$B$16*$B$9/$D$16,0)) -> 1200 | C38: =IF(A38=$B$13+$D$17,($B$17*$B$9/$D$17)*(1-$B$14),IF(A38<$B$13+$D$17,$B$17*$B$9/$D$17,0)) -> 562.5 | D38: =IF(A38=$B$13+$D$18,($B$18*$B$9/$D$18)*(1-$B$14),IF(A38<$B$13+$D$18,$B$18*$B$9/$D$18,0)) -> 900 | E38: =IF(A38=$B$13+$D$19,($B$19*$B$9/$D$19)*(1-$B$14),IF(A38<$B$13+$D$19,$B$19*$B$9/$D$19,0)) -> 1500 | F38: =IF(A38=$B$13+$D$20,($B$20/$D$20)*(1-$B$14),IF(A38<$B$13+$D$20,$B$20/$D$20,0)) -> 0 | G38: =SUM(B38:F38) -> 4162.5 | H38: =B38+C38 -> 1762.5 | I38: =$B$9*($B$16+$B$17)-V38 -> 59587.5 | J38: =$B$9*($B$18)-X38 -> 10800 | K38: =$B$9*($B$19)-Y38 -> 3000 | L38: =$B$20-Z38+AJ38 -> 0 | N38: =$B$9*$B$15 -> 22500 | O38: =SUM(I38:N38) -> 95887.5 | P38: =V37 -> 21150 | Q38: 0 | R38: =X37 -> 10800 | S38: =Y37 -> 18000 | T38: =Z37 -> 0 | U38: =AB37 -> 49950 | V38: =P38+H38 -> 22912.5 | W38: 0 | X38: =R38+D38 -> 11700 | Y38: =S38+E38 -> 19500 | Z38: =T38+F38 -> 0 | AB38: =SUM(V38:AA38) -> 54112.5
A39: =A38+1 -> 2038 | B39: =IF(A39=$B$13+$D$16,($B$16*$B$9/$D$16)*(1-$B$14),IF(A39<$B$13+$D$16,$B$16*$B$9/$D$16,0)) -> 1200 | C39: =IF(A39=$B$13+$D$17,($B$17*$B$9/$D$17)*(1-$B$14),IF(A39<$B$13+$D$17,$B$17*$B$9/$D$17,0)) -> 562.5 | D39: =IF(A39=$B$13+$D$18,($B$18*$B$9/$D$18)*(1-$B$14),IF(A39<$B$13+$D$18,$B$18*$B$9/$D$18,0)) -> 900 | E39: =IF(A39=$B$13+$D$19,($B$19*$B$9/$D$19)*(1-$B$14),IF(A39<$B$13+$D$19,$B$19*$B$9/$D$19,0)) -> 1500 | F39: =IF(A39=$B$13+$D$20,($B$20/$D$20)*(1-$B$14),IF(A39<$B$13+$D$20,$B$20/$D$20,0)) -> 0 | G39: =SUM(B39:F39) -> 4162.5 | H39: =B39+C39 -> 1762.5 | I39: =$B$9*($B$16+$B$17)-V39 -> 57825 | J39: =$B$9*($B$18)-X39 -> 9900 | K39: =$B$9*($B$19)-Y39 -> 1500 | L39: =$B$20-Z39+AJ39 -> 0 | N39: =$B$9*$B$15 -> 22500 | O39: =SUM(I39:N39) -> 91725 | P39: =V38 -> 22912.5 | Q39: 0 | R39: =X38 -> 11700 | S39: =Y38 -> 19500 | T39: =Z38 -> 0 | U39: =AB38 -> 54112.5 | V39: =P39+H39 -> 24675 | W39: 0 | X39: =R39+D39 -> 12600 | Y39: =S39+E39 -> 21000 | Z39: =T39+F39 -> 0 | AB39: =SUM(V39:AA39) -> 58275
... A76: =A75+1 -> 2075 | B76: =IF(A76=$B$13+$D$16,($B$16*$B$9/$D$16)*(1-$B$14),IF(A76<$B$13+$D$16,$B$16*$B$9/$D$16,0)) -> 0 | C76: =IF(A76=$B$13+$D$17,($B$17*$B$9/$D$17)*(1-$B$14),IF(A76<$B$13+$D$17,$B$17*$B$9/$D$17,0)) -> 0 | D76: =IF(A76=$B$13+$D$18,($B$18*$B$9/$D$18)*(1-$B$14),IF(A76<$B$13+$D$18,$B$18*$B$9/$D$18,0)) -> 0 | E76: =IF(A76=$B$13+$D$19,($B$19*$B$9/$D$19)*(1-$B$14),IF(A76<$B$13+$D$19,$B$19*$B$9/$D$19,0)) -> 0 | F76: =IF(A76=$B$13+$D$20,($B$20/$D$20)*(1-$B$14),IF(A76<$B$13+$D$20,$B$20/$D$20,0)) -> 0 | G76: =SUM(B76:F76) -> 0 | H76: =B76+C76 -> 0 | I76: =$B$9*($B$16+$B$17)-V76 -> 0 | J76: =$B$9*($B$18)-X76 -> 0 | K76: =$B$9*($B$19)-Y76 -> 0 | L76: =$B$20-Z76+AJ76 -> 0 | N76: =$B$9*$B$15 -> 22500 | O76: =SUM(I76:N76) -> 22500 | P76: =V75 -> 82500 | Q76: 0 | R76: =X75 -> 22500 | S76: =Y75 -> 22500 | T76: =Z75 -> 0 | U76: =AB75 -> 127500 | V76: =P76+H76 -> 82500 | W76: 0 | X76: =R76+D76 -> 22500 | Y76: =S76+E76 -> 22500 | Z76: =T76+F76 -> 0 | AB76: =SUM(V76:AA76) -> 127500
A80: ETAPE 3 : Compte de resultat
A82: Année | B82: =F13 -> 2025 | D82: Année | E82: =F13+1 -> 2026
A83: Dotation aux ammortissements (année en cours) | B83: {=INDIRECT(ADDRESS(H13,7))} -> 4162.5 | D83: Dotation aux ammortissements (année en cours) | E83: {=INDIRECT(ADDRESS(H13+1,7))} -> 4162.5
A84: Loyer | B84: 8000 | D84: Loyer | E84: =8000 -> 8000
A85: Charges | B85: =1200+9000 -> 10200 | D85: Charges | E85: =1200 -> 1200
A86: Taxes | B86: 0 | D86: Taxes | E86: 0
A87: Interets d'emprunts | B87: =3000 -> 3000 | D87: Interets d'emprunts | E87: 3000
A88: Resultat comptable avant dotation aux amortissements | B88: =B84-B85-B86-B87 -> -5200 | D88: Resultat comptable avant dotation aux amortissements | E88: =E84-E85-E86-E87 -> 3800
A89: Déficits reportables (Nouvellement crée) | B89: =IF(B88<0,-B88,0) -> 5200 | D89: Déficits reportables (Nouvellement crée) | E89: =IF(E88<0,-E88,0) -> 0
A90: Resultat comptable après dotation aux amortissements | B90: =B88-B83 -> -9362.5 | D90: Resultat comptable après dotation aux amortissements | E90: =E88-E83 -> -362.5
A91: Amortissement excédentaires (Nouvellement crée) | B91: =MIN(B83 , MAX(0 , B83 - B88)) -> 4162.5 | C91: =max(0-B90-B89) -> 4162.5 | D91: Amortissement excédentaires | E91: =MIN(E83 , MAX(0 , E83 - E88)) -> 362.5
A92: Résultat après imputation des amortissements excédentaires | B92: =B91+B90 -> -5200 | D92: Résultat après imputation des amortissements excédentaires | E92: =E91+E90 -> 0
A93: Amortissement excédentaires ANTERIEURS | B93: 0 | D93: Amortissement excédentaires ANTERIEURS | E93: =B96 -> 4162.5
A94: Amortissement ANTERIEURS imputés | B94: =IF(B90<=0,0,MIN(B90,B93)) -> 0 | D94: Amortissement ANTERIEURS imputés | E94: =IF(E90<=0,0,MIN(E90,E93)) -> 0
A95: Amortissement ANTERIEURS restants | B95: =B93-B94 -> 0 | D95: Amortissement ANTERIEURS restants | E95: =E93-E94 -> 4162.5
A96: Amortissements restants à reporter pour les années ultérieures | B96: =B95+B91 -> 4162.5 | D96: Amortissements restants à reporter pour les années ultérieures | E96: =E95+E91 -> 4525
A97: Résultat après imputation des amortisseùents excédentaires ANTERIEURS | B97: =B92-B94 -> -5200 | D97: Résultat après imputation des amortisseùents excédentaires ANTERIEURS | E97: =E92-E94 -> 0
A98: Déficits ANTERIEURS | B98: 0 | D98: Déficits ANTERIEURS | E98: =B101 -> 5200
A99: Déficits ANTERIEURS imputés | B99: =IF(B97<=0,0,MIN(B97,B98)) -> 0 | D99: Déficits ANTERIEURS imputés | E99: =IF(E97<=0,0,MIN(E97,E98)) -> 0
A100: Déficits ANTERIEURS restants | B100: =B98+B99 -> 0 | D100: Déficits ANTERIEURS restants | E100: =E98+E99 -> 5200
A101: Déficits restants à reportrer pour les années ultérieures | B101: =B100+B89 -> 5200 | D101: Déficits restants à reportrer pour les années ultérieures | E101: =E100+E89 -> 5200
A102: Resultat fiscal après imputation : 1/ amortissements excedentaires de l'année en cours 2/ amortissement excédentaires antérieurs 3/ déficits antérieurs | B102: =MAX(0 , B88 - B83) -> 0 | D102: Resultat fiscal après imputation : 1/ amortissements excedentaires de l'année en cours 2/ amortissement excédentaires antérieurs 3/ déficits antérieurs | E102: =MAX(0 , E88 - E83) -> 0
A103: Disponibilité Antérieurs | B103: 0 | D103: Disponibilité Antérieurs | E103: =B104 -> 0
A104: Disponibilités | B104: =Max(0,B84-B85-B86-B87)+B103 -> 0 | D104: Disponibilités | E104: =Max(0,E84-E85-E86-E87)+E103 -> 3800
A107: ETAPE 4 : LES FORMULAIRES BILAN (2033-A)
A108: Année | B108: =F13 -> 2025 | I108: Année | J108: =F13+1 -> 2026
B109: ACTIF | C109: BRUT | E109: Amortissement/provisions | G109: Net Exercice N | J109: ACTIF | K109: BRUT | M109: Amortissement/provisions | O109: Net Exercice N
A110: Actif immobilisé | B110: Immobilisation corporelles | C110: "028" | D110: =B4+B5 -> 150000 | E110: "030" | F110: {=INDIRECT(ADDRESS(H13,28))} -> 4162.5 | G110: =D110-F110 -> 145837.5 | I110: Actif immobilisé | J110: Immobilisation corporelles | K110: "028" | L110: =D110 -> 150000 | M110: "030" | N110: {=INDIRECT(ADDRESS(H13+1,28))} -> 8325 | O110: =L110-N110 -> 141675
B111: Immobilisation financière | C111: "040" | D111: 0 | E111: "042" | F111: 0 | G111: 0 | J111: Immobilisation financière | K111: "040" | L111: 0 | M111: "042" | N111: 0 | O111: 0
B112: Total | C112: "044" | D112: =D110+D111 -> 150000 | E112: "048" | F112: =F110+F111 -> 4162.5 | G112: =G110+G111 -> 145837.5 | J112: Total | K112: "044" | L112: =L110+L111 -> 150000 | M112: "048" | N112: =N110+N111 -> 8325 | O112: =O110+O111 -> 141675
A113: Actif Circulant | I113: Actif Circulant
B114: Disponibilités | C114: "084" | D114: =B104 -> 0 | G114: =D114 -> 0 | J114: Disponibilités | K114: "084" | L114: =J104 | O114: =L114
A116: Total | C116: "110" | D116: =D112+D114 -> 150000 | E116: "112" | F116: =F112 -> 4162.5 | G116: =G112+G114 -> 145837.5 | I116: Total | K116: "110" | L116: =L112+L114 -> 150000 | M116: "112" | N116: =N112 -> 8325 | O116: =O112+O114 -> 141675
B117: PASSIF | G117: Net Exercice N | J117: PASSIF | O117: Net Exercice N
B118: Capital social ou individuel | C118: "120" | G118: =G116-G120-G122 -> 67200 | J118: Capital social ou individuel | K118: "120" | O118: =O116-O120-O122 -> 53675
B120: Resultat de l'exercice | C120: "136" | G120: =B90 -> -9362.5 | J120: Resultat de l'exercice | K120: "136" | O120: =J90
B122: Emrpunt et dettes assimilés | C122: "156" | G122: =88000 -> 88000 | J122: Emrpunt et dettes assimilés | K122: "156" | O122: =88000 -> 88000
B123: Total II | C123: "176" | G123: =G122 -> 88000 | J123: Total II | K123: "176" | O123: =O122 -> 88000
B124: Total III | C124: "180" | G124: =SUM(G118:G122) -> 145837.5 | J124: Total III | K124: "180" | O124: =SUM(O118:O122) -> 141675
A127: 2033-B | E127: Equilibre | F127: =IF(((B88 - B83) + C142)=B102,"C'est bon","C'est pas bon") -> C'est pas bon | J127: Equilibre | K127: =IF(((E88 - E83) + I142)=E102,"C'est bon","C'est pas bon") -> C'est bon
B128: =F13 -> 2025 | H128: =F13+1 -> 2026
A129: A- RESULTAT COMPTABLE | G129: A- RESULTAT COMPTABLE
A130: production vendue : services | B130: "218" | C130: =B84 -> 8000 | G130: production vendue : services | H130: "218" | I130: =E84 -> 8000
A131: Total produit d'exploitation | B131: "232" | C131: =C130 -> 8000 | G131: Total produit d'exploitation | H131: "232" | I131: =I130 -> 8000
A132: Autre charges externes | B132: "242" | C132: =B85 -> 10200 | G132: Autre charges externes | H132: "242" | I132: =E85 -> 1200
A133: Impots taxe et versement assimilés | B133: "244" | C133: =B86 -> 0 | G133: Impots taxe et versement assimilés | H133: "244" | I133: =E86 -> 0
A134: Dotations aux amortissements | B134: "254" | C134: =B83 -> 4162.5 | G134: Dotations aux amortissements | H134: "254" | I134: =E83 -> 4162.5
A135: Total charges d'exploitation | B135: "264" | C135: =SUM(C132:C134) -> 14362.5 | G135: Total charges d'exploitation | H135: "264" | I135: =SUM(I132:I134) -> 5362.5
A136: Resultat d'exploitation | B136: "270" | C136: =C131-C135 -> -6362.5 | G136: Resultat d'exploitation | H136: "270" | I136: =I131-I135 -> 2637.5
A137: Charges financières | B137: "294" | C137: =B87 -> 3000 | G137: Charges financières | H137: "294" | I137: =E87 -> 3000
A138: Benefices ou perte | B138: "310" | C138: =B90 -> -9362.5 | G138: Benefices ou perte | H138: "310" | I138: =E90 -> -362.5
A139: B- RESULTAT FISCAL | G139: B- RESULTAT FISCAL
A140: Reporter les benef compables | B140: "312" | C140: =Max(0,C138) -> 0 | D140: "314" | E140: =-MIN(0,C138) -> 9362.5 | G140: Reporter les benef compables | H140: "312" | I140: =Max(0,I138) -> 0 | J140: "314" | K140: =-MIN(0,I138) -> 362.5
A141: Amortissements excedentaires | B141: "318" | C141: =B91 -> 4162.5 | D141: "342" | E141: =IF(B88 > 0 , MIN(B88 , B83) , 0) -> 0 | G141: Amortissements excedentaires | H141: "318" | I141: =E91 -> 362.5 | J141: "342" | K141: =IF(E88 > 0 , MIN(E88 , E83) , 0) -> 3800
A142: En ligne : deduction de l'execice : deduction diverses Papier : creance du au titre du report en arrière du deficit | B142: "350" | C142: =B91 -> 4162.5 | D142: "360" | E142: =IF(B88 < 0 , ABS(B88) , 0) -> 5200 | G142: En ligne : deduction de l'execice : deduction diverses Papier : creance du au titre du report en arrière du deficit | H142: "350" | I142: =E91 -> 362.5 | J142: "360" | K142: =IF(E88 < 0 , ABS(E88) , 0) -> 0
A143: Resultat Fiscal avant imputation | B143: "352" | C143: =IF(B97>0,B97,0) -> 0 | D143: "354" | E143: =IF(B97<0,-B97,0) -> 5200 | G143: Resultat Fiscal avant imputation | H143: "352" | I143: =IF(E97>0,E97,0) -> 0 | J143: "354" | K143: =IF(E97<0,-E97,0) -> 0
A144: Resultat Fiscal apres imputation | B144: "370" | C144: =MAX(0 , B88 - B83) -> 0 | D144: "372" | E144: =IF(B102<0,-B102,0) -> 0 | G144: Resultat Fiscal | H144: "370" | I144: =MAX(0 , E88 - E83) -> 0 | J144: "372" | K144: =IF(E102<0,-E102,0) -> 0
A146: 2033-C
A147: 1- Immobilisations
A149: Année | B149: =F13 -> 2025 | K149: Année | L149: =F13+1 -> 2026
B151: Valeur brut des immo en début d'exercice | D151: Augmentation | F151: Diminution | H151: Valeur brute des immo à la fin de l'exercice | L151: Valeur brut des immo en début d'exercice | N151: Augmentation | P151: Diminution | R151: Valeur brute des immo à la fin de l'exercice
A152: Terrains | B152: "420" | C152: 0 | D152: "422" | E152: =IF(F13=B13,B9*B15,0) -> 22500 | F152: "424" | G152: 0 | H152: "426" | I152: =C152+E152+G152 -> 22500 | K152: Terrains | L152: "420" | M152: =I152 -> 22500 | N152: "422" | O152: 0 | P152: "424" | Q152: 0 | R152: "426" | S152: =M152+O152+Q152 -> 22500
A153: Constructions | B153: "430" | C153: 0 | D153: "432" | E153: =IF(F13=B13,B9*(B16+B17),0) -> 82500 | F153: "434" | G153: 0 | H153: "436" | I153: =C153+E153+G153 -> 82500 | K153: Constructions | L153: "430" | M153: =I153 -> 82500 | N153: "432" | O153: 0 | P153: "434" | Q153: 0 | R153: "436" | S153: =M153+O153+Q153 -> 82500
...

Sheet Appartement 2
A1: Etape 1 prix de départ Appartement 2: | D1: Espace Pro : impot gouv : Déclarer : Résultat
A4: Prix d'achat | B4: 150000
A5: Frais de notaire | B5: =0 -> 0
A6: frais d'agence | B6: =0 -> 0
A7: Mobilier | B7: =0 -> 0
A8: Travaux à amortir | B8: =0 -> 0
A9: Base amortissable | B9: =IF(B4>0,SUM(B4:B6),IF(E4>0,E4,0)) -> 150000
A11: Etape 2 : Décomposition et amortissement
A12: Date de début d'activité | B12: 45658
A13: Année de début d'activité | B13: =YEAR(B12) -> 2025 | E13: Année d'exercice | F13: =YEAR(TODAY())-1 -> 2025 | H13: =F13-B13+26 -> 26
A14: Prorata | B14: =YEARFRAC(B12,DATE(YEAR(B12)+1,1,1),4) -> 1 | AD14: Travaux/Mobilier | AE14: Montant | AF14: Date debut | AG14: Nbr année amortissement | AH14: Prorata première année
A15: Terrain | B15: =15% -> 0.15 | AD15: Travaux/Mobilier 1 | AE15: 0 | AF15: 45809 | AG15: 10 | AH15: =YEARFRAC(AF15,DATE(YEAR(AF15)+1,1,1),4) -> 0.58333333
A16: Structure (Gros oeuvre) | B16: =40% -> 0.4 | C16: du total sur | D16: 50 | E16: ans | AD16: Travaux/Mobilier 2 | AE16: 0 | AF16: 46174 | AG16: 10 | AH16: =YEARFRAC(AF16,DATE(YEAR(AF16)+1,1,1),4) -> 0.58333333
A17: Façade, étanchieté | B17: =15% -> 0.15 | C17: du total sur | D17: 40 | E17: ans | AD17: Travaux/Mobilier 3 | AE17: 0 | AF17: 46539 | AG17: 10 | AH17: =YEARFRAC(AF17,DATE(YEAR(AF17)+1,1,1),4) -> 0.58333333
A18: IGT, Equipement | B18: =15% -> 0.15 | C18: du total sur | D18: 25 | E18: ans | AD18: Travaux/Mobilier 4 | AE18: 0 | AF18: 46905 | AG18: 10 | AH18: =YEARFRAC(AF18,DATE(YEAR(AF18)+1,1,1),4) -> 0.58333333
A19: Agencements (cloisons, chapes, platerie, revetement, plomberie, cablage) | B19: =15% -> 0.15 | C19: du total sur | D19: 15 | E19: ans | AD19: Travaux/Mobilier 5 | AE19: 0 | AF19: 47270 | AG19: 10 | AH19: =YEARFRAC(AF19,DATE(YEAR(AF19)+1,1,1),4) -> 0.58333333
A20: Mobilier+travaux avant 1ere location | B20: =B7+B8 -> 0 | D20: 10 | E20: ans | AD20: Travaux/Mobilier 6 | AE20: 0 | AF20: 47635 | AG20: 10 | AH20: =YEARFRAC(AF20,DATE(YEAR(AF20)+1,1,1),4) -> 0.58333333
A21: Frais de notaire | B21: =B5 -> 0 | D21: 0 | AD21: Travaux/Mobilier 7 | AE21: 0 | AF21: 48000 | AG21: 10 | AH21: =YEARFRAC(AF21,DATE(YEAR(AF21)+1,1,1),4) -> 0.58333333
A22: Frais d'agence | B22: =B6 -> 0 | D22: 0 | AD22: Travaux/Mobilier 8 | AE22: 0 | AF22: 48000 | AG22: 10 | AH22: =YEARFRAC(AF22,DATE(YEAR(AF22)+1,1,1),4) -> 0.58333333
AD23: Travaux/Mobilier 9 | AE23: 0 | AF23: 48000 | AG23: 10 | AH23: =YEARFRAC(AF23,DATE(YEAR(AF23)+1,1,1),4) -> 0.58333333
C24: Augmentation Amortissement (dotations) | K24: Immobilisations net | Q24: Ammortissement début d'excercice | W24: Ammortissement fin exercice | AD24: Travaux/Mobilier 10 | AE24: 0 | AF24: 48000 | AG24: 10 | AH24: =YEARFRAC(AF24,DATE(YEAR(AF24)+1,1,1),4) -> 0.58333333
A25: Année | B25: Structure | C25: Façade | D25: Equipement | E25: Agencement | F25: Autres immobilisations corporelles | G25: Total Ammortissement | H25: Construction | I25: Construction | J25: Immo equipement | K25: Immo agencement | L25: Autres immobilisations corporelles | N25: Terrain | O25: Total | P25: Construction | Q25: Terrain | R25: Equipement | S25: Agencement | T25: Autres immobilisations corporelles | U25: Total | V25: Construction | W25: Terrain | X25: Equipement | Y25: Agencement | Z25: Autres immobilisations corporelles | AB25: Total
A26: 2025 | B26: =IF(A26<$B$13+$D$16,$B$16*$B$9/$D$16,0)*B14 -> 1200 | C26: =IF(A26<$B$13+$D17,$B$17*$B$9/$D$17,0)*B14 -> 562.5 | D26: =IF(A26<$B$13+$D18,$B$18*$B$9/$D$18,0)*B14 -> 900 | E26: =IF(A26<$B$13+$D$19,$B$19*$B$9/$D$19,0)*B14 -> 1500 | F26: =(IF(A26<$B$13+$D$20,$B$20/$D$20,0)*B14) -> 0 | G26: =SUM(B26:F26) -> 4162.5 | H26: =B26+C26 -> 1762.5 | I26: =$B$9*($B$16+$B$17)-V26 -> 80737.5 | J26: =$B$9*($B$18)-X26 -> 21600 | K26: =$B$9*($B$19)-Y26 -> 21000 | L26: =$B$20-Z26+AJ26 -> 0 | N26: =$B$9*$B$15 -> 22500 | O26: =SUM(I26:N26) -> 145837.5 | P26: 0 | Q26: 0 | R26: 0 | S26: 0 | T26: 0 | U26: 0 | V26: =P26+H26 -> 1762.5 | W26: 0 | X26: =R26+D26 -> 900 | Y26: =S26+E26 -> 1500 | Z26: =T26+F26 -> 0 | AB26: =SUM(V26:AA26) -> 4162.5
A27: 2026 | B27: =IF(A27=$B$13+$D$16,($B$16*$B$9/$D$16)*(1-$B$14),IF(A27<$B$13+$D$16,$B$16*$B$9/$D$16,0)) -> 1200 | C27: =IF(A27=$B$13+$D$17,($B$17*$B$9/$D$17)*(1-$B$14),IF(A27<$B$13+$D$17,$B$17*$B$9/$D$17,0)) -> 562.5 | D27: =IF(A27=$B$13+$D$18,($B$18*$B$9/$D$18)*(1-$B$14),IF(A27<$B$13+$D$18,$B$18*$B$9/$D$18,0)) -> 900 | E27: =IF(A27=$B$13+$D$19,($B$19*$B$9/$D$19)*(1-$B$14),IF(A27<$B$13+$D$19,$B$19*$B$9/$D$19,0)) -> 1500 | F27: =IF(A27=$B$13+$D$20,($B$20/$D$20)*(1-$B$14),IF(A27<$B$13+$D$20,$B$20/$D$20,0)) -> 0 | G27: =SUM(B27:F27) -> 4162.5 | H27: =B27+C27 -> 1762.5 | I27: =$B$9*($B$16+$B$17)-V27 -> 78975 | J27: =$B$9*($B$18)-X27 -> 20700 | K27: =$B$9*($B$19)-Y27 -> 19500 | L27: =$B$20-Z27+AJ27 -> 0 | N27: =$B$9*$B$15 -> 22500 | O27: =SUM(I27:N27) -> 141675 | P27: =V26 -> 1762.5 | Q27: 0 | R27: =X26 -> 900 | S27: =Y26 -> 1500 | T27: =Z26 -> 0 | U27: =AB26 -> 4162.5 | V27: =P27+H27 -> 3525 | W27: 0 | X27: =R27+D27 -> 1800 | Y27: =S27+E27 -> 3000 | Z27: =T27+F27 -> 0 | AB27: =SUM(V27:AA27) -> 8325
A28: =A27+1 -> 2027 | B28: =IF(A28=$B$13+$D$16,($B$16*$B$9/$D$16)*(1-$B$14),IF(A28<$B$13+$D$16,$B$16*$B$9/$D$16,0)) -> 1200 | C28: =IF(A28=$B$13+$D$17,($B$17*$B$9/$D$17)*(1-$B$14),IF(A28<$B$13+$D$17,$B$17*$B$9/$D$17,0)) -> 562.5 | D28: =IF(A28=$B$13+$D$18,($B$18*$B$9/$D$18)*(1-$B$14),IF(A28<$B$13+$D$18,$B$18*$B$9/$D$18,0)) -> 900 | E28: =IF(A28=$B$13+$D$19,($B$19*$B$9/$D$19)*(1-$B$14),IF(A28<$B$13+$D$19,$B$19*$B$9/$D$19,0)) -> 1500 | F28: =IF(A28=$B$13+$D$20,($B$20/$D$20)*(1-$B$14),IF(A28<$B$13+$D$20,$B$20/$D$20,0)) -> 0 | G28: =SUM(B28:F28) -> 4162.5 | H28: =B28+C28 -> 1762.5 | I28: =$B$9*($B$16+$B$17)-V28 -> 77212.5 | J28: =$B$9*($B$18)-X28 -> 19800 | K28: =$B$9*($B$19)-Y28 -> 18000 | L28: =$B$20-Z28+AJ28 -> 0 | N28: =$B$9*$B$15 -> 22500 | O28: =SUM(I28:N28) -> 137512.5 | P28: =V27 -> 3525 | Q28: 0 | R28: =X27 -> 1800 | S28: =Y27 -> 3000 | T28: =Z27 -> 0 | U28: =AB27 -> 8325 | V28: =P28+H28 -> 5287.5 | W28: 0 | X28: =R28+D28 -> 2700 | Y28: =S28+E28 -> 4500 | Z28: =T28+F28 -> 0 | AB28: =SUM(V28:AA28) -> 12487.5
A29: =A28+1 -> 2028 | B29: =IF(A29=$B$13+$D$16,($B$16*$B$9/$D$16)*(1-$B$14),IF(A29<$B$13+$D$16,$B$16*$B$9/$D$16,0)) -> 1200 | C29: =IF(A29=$B$13+$D$17,($B$17*$B$9/$D$17)*(1-$B$14),IF(A29<$B$13+$D$17,$B$17*$B$9/$D$17,0)) -> 562.5 | D29: =IF(A29=$B$13+$D$18,($B$18*$B$9/$D$18)*(1-$B$14),IF(A29<$B$13+$D$18,$B$18*$B$9/$D$18,0)) -> 900 | E29: =IF(A29=$B$13+$D$19,($B$19*$B$9/$D$19)*(1-$B$14),IF(A29<$B$13+$D$19,$B$19*$B$9/$D$19,0)) -> 1500 | F29: =IF(A29=$B$13+$D$20,($B$20/$D$20)*(1-$B$14),IF(A29<$B$13+$D$20,$B$20/$D$20,0)) -> 0 | G29: =SUM(B29:F29) -> 4162.5 | H29: =B29+C29 -> 1762.5 | I29: =$B$9*($B$16+$B$17)-V29 -> 75450 | J29: =$B$9*($B$18)-X29 -> 18900 | K29: =$B$9*($B$19)-Y29 -> 16500 | L29: =$B$20-Z29+AJ29 -> 0 | N29: =$B$9*$B$15 -> 22500 | O29: =SUM(I29:N29) -> 133350 | P29: =V28 -> 5287.5 | Q29: 0 | R29: =X28 -> 2700 | S29: =Y28 -> 4500 | T29: =Z28 -> 0 | U29: =AB28 -> 12487.5 | V29: =P29+H29 -> 7050 | W29: 0 | X29: =R29+D29 -> 3600 | Y29: =S29+E29 -> 6000 | Z29: =T29+F29 -> 0 | AB29: =SUM(V29:AA29) -> 16650
A30: =A29+1 -> 2029 | B30: =IF(A30=$B$13+$D$16,($B$16*$B$9/$D$16)*(1-$B$14),IF(A30<$B$13+$D$16,$B$16*$B$9/$D$16,0)) -> 1200 | C30: =IF(A30=$B$13+$D$17,($B$17*$B$9/$D$17)*(1-$B$14),IF(A30<$B$13+$D$17,$B$17*$B$9/$D$17,0)) -> 562.5 | D30: =IF(A30=$B$13+$D$18,($B$18*$B$9/$D$18)*(1-$B$14),IF(A30<$B$13+$D$18,$B$18*$B$9/$D$18,0)) -> 900 | E30: =IF(A30=$B$13+$D$19,($B$19*$B$9/$D$19)*(1-$B$14),IF(A30<$B$13+$D$19,$B$19*$B$9/$D$19,0)) -> 1500 | F30: =IF(A30=$B$13+$D$20,($B$20/$D$20)*(1-$B$14),IF(A30<$B$13+$D$20,$B$20/$D$20,0)) -> 0 | G30: =SUM(B30:F30) -> 4162.5 | H30: =B30+C30 -> 1762.5 | I30: =$B$9*($B$16+$B$17)-V30 -> 73687.5 | J30: =$B$9*($B$18)-X30 -> 18000 | K30: =$B$9*($B$19)-Y30 -> 15000 | L30: =$B$20-Z30+AJ30 -> 0 | N30: =$B$9*$B$15 -> 22500 | O30: =SUM(I30:N30) -> 129187.5 | P30: =V29 -> 7050 | Q30: 0 | R30: =X29 -> 3600 | S30: =Y29 -> 6000 | T30: =Z29 -> 0 | U30: =AB29 -> 16650 | V30: =P30+H30 -> 8812.5 | W30: 0 | X30: =R30+D30 -> 4500 | Y30: =S30+E30 -> 7500 | Z30: =T30+F30 -> 0 | AB30: =SUM(V30:AA30) -> 20812.5
A31: =A30+1 -> 2030 | B31: =IF(A31=$B$13+$D$16,($B$16*$B$9/$D$16)*(1-$B$14),IF(A31<$B$13+$D$16,$B$16*$B$9/$D$16,0)) -> 1200 | C31: =IF(A31=$B$13+$D$17,($B$17*$B$9/$D$17)*(1-$B$14),IF(A31<$B$13+$D$17,$B$17*$B$9/$D$17,0)) -> 562.5 | D31: =IF(A31=$B$13+$D$18,($B$18*$B$9/$D$18)*(1-$B$14),IF(A31<$B$13+$D$18,$B$18*$B$9/$D$18,0)) -> 900 | E31: =IF(A31=$B$13+$D$19,($B$19*$B$9/$D$19)*(1-$B$14),IF(A31<$B$13+$D$19,$B$19*$B$9/$D$19,0)) -> 1500 | F31: =IF(A31=$B$13+$D$20,($B$20/$D$20)*(1-$B$14),IF(A31<$B$13+$D$20,$B$20/$D$20,0)) -> 0 | G31: =SUM(B31:F31) -> 4162.5 | H31: =B31+C31 -> 1762.5 | I31: =$B$9*($B$16+$B$17)-V31 -> 71925 | J31: =$B$9*($B$18)-X31 -> 17100 | K31: =$B$9*($B$19)-Y31 -> 13500 | L31: =$B$20-Z31+AJ31 -> 0 | N31: =$B$9*$B$15 -> 22500 | O31: =SUM(I31:N31) -> 125025 | P31: =V30 -> 8812.5 | Q31: 0 | R31: =X30 -> 4500 | S31: =Y30 -> 7500 | T31: =Z30 -> 0 | U31: =AB30 -> 20812.5 | V31: =P31+H31 -> 10575 | W31: 0 | X31: =R31+D31 -> 5400 | Y31: =S31+E31 -> 9000 | Z31: =T31+F31 -> 0 | AB31: =SUM(V31:AA31) -> 24975
A32: =A31+1 -> 2031 | B32: =IF(A32=$B$13+$D$16,($B$16*$B$9/$D$16)*(1-$B$14),IF(A32<$B$13+$D$16,$B$16*$B$9/$D$16,0)) -> 1200 | C32: =IF(A32=$B$13+$D$17,($B$17*$B$9/$D$17)*(1-$B$14),IF(A32<$B$13+$D$17,$B$17*$B$9/$D$17,0)) -> 562.5 | D32: =IF(A32=$B$13+$D$18,($B$18*$B$9/$D$18)*(1-$B$14),IF(A32<$B$13+$D$18,$B$18*$B$9/$D$18,0)) -> 900 | E32: =IF(A32=$B$13+$D$19,($B$19*$B$9/$D$19)*(1-$B$14),IF(A32<$B$13+$D$19,$B$19*$B$9/$D$19,0)) -> 1500 | F32: =IF(A32=$B$13+$D$20,($B$20/$D$20)*(1-$B$14),IF(A32<$B$13+$D$20,$B$20/$D$20,0)) -> 0 | G32: =SUM(B32:F32) -> 4162.5 | H32: =B32+C32 -> 1762.5 | I32: =$B$9*($B$16+$B$17)-V32 -> 70162.5 | J32: =$B$9*($B$18)-X32 -> 16200 | K32: =$B$9*($B$19)-Y32 -> 12000 | L32: =$B$20-Z32+AJ32 -> 0 | N32: =$B$9*$B$15 -> 22500 | O32: =SUM(I32:N32) -> 120862.5 | P32: =V31 -> 10575 | Q32: 0 | R32: =X31 -> 5400 | S32: =Y31 -> 9000 | T32: =Z31 -> 0 | U32: =AB31 -> 24975 | V32: =P32+H32 -> 12337.5 | W32: 0 | X32: =R32+D32 -> 6300 | Y32: =S32+E32 -> 10500 | Z32: =T32+F32 -> 0 | AB32: =SUM(V32:AA32) -> 29137.5
A33: =A32+1 -> 2032 | B33: =IF(A33=$B$13+$D$16,($B$16*$B$9/$D$16)*(1-$B$14),IF(A33<$B$13+$D$16,$B$16*$B$9/$D$16,0)) -> 1200 | C33: =IF(A33=$B$13+$D$17,($B$17*$B$9/$D$17)*(1-$B$14),IF(A33<$B$13+$D$17,$B$17*$B$9/$D$17,0)) -> 562.5 | D33: =IF(A33=$B$13+$D$18,($B$18*$B$9/$D$18)*(1-$B$14),IF(A33<$B$13+$D$18,$B$18*$B$9/$D$18,0)) -> 900 | E33: =IF(A33=$B$13+$D$19,($B$19*$B$9/$D$19)*(1-$B$14),IF(A33<$B$13+$D$19,$B$19*$B$9/$D$19,0)) -> 1500 | F33: =IF(A33=$B$13+$D$20,($B$20/$D$20)*(1-$B$14),IF(A33<$B$13+$D$20,$B$20/$D$20,0)) -> 0 | G33: =SUM(B33:F33) -> 4162.5 | H33: =B33+C33 -> 1762.5 | I33: =$B$9*($B$16+$B$17)-V33 -> 68400 | J33: =$B$9*($B$18)-X33 -> 15300 | K33: =$B$9*($B$19)-Y33 -> 10500 | L33: =$B$20-Z33+AJ33 -> 0 | N33: =$B$9*$B$15 -> 22500 | O33: =SUM(I33:N33) -> 116700 | P33: =V32 -> 12337.5 | Q33: 0 | R33: =X32 -> 6300 | S33: =Y32 -> 10500 | T33: =Z32 -> 0 | U33: =AB32 -> 29137.5 | V33: =P33+H33 -> 14100 | W33: 0 | X33: =R33+D33 -> 7200 | Y33: =S33+E33 -> 12000 | Z33: =T33+F33 -> 0 | AB33: =SUM(V33:AA33) -> 33300
A34: =A33+1 -> 2033 | B34: =IF(A34=$B$13+$D$16,($B$16*$B$9/$D$16)*(1-$B$14),IF(A34<$B$13+$D$16,$B$16*$B$9/$D$16,0)) -> 1200 | C34: =IF(A34=$B$13+$D$17,($B$17*$B$9/$D$17)*(1-$B$14),IF(A34<$B$13+$D$17,$B$17*$B$9/$D$17,0)) -> 562.5 | D34: =IF(A34=$B$13+$D$18,($B$18*$B$9/$D$18)*(1-$B$14),IF(A34<$B$13+$D$18,$B$18*$B$9/$D$18,0)) -> 900 | E34: =IF(A34=$B$13+$D$19,($B$19*$B$9/$D$19)*(1-$B$14),IF(A34<$B$13+$D$19,$B$19*$B$9/$D$19,0)) -> 1500 | F34: =IF(A34=$B$13+$D$20,($B$20/$D$20)*(1-$B$14),IF(A34<$B$13+$D$20,$B$20/$D$20,0)) -> 0 | G34: =SUM(B34:F34) -> 4162.5 | H34: =B34+C34 -> 1762.5 | I34: =$B$9*($B$16+$B$17)-V34 -> 66637.5 | J34: =$B$9*($B$18)-X34 -> 14400 | K34: =$B$9*($B$19)-Y34 -> 9000 | L34: =$B$20-Z34+AJ34 -> 0 | N34: =$B$9*$B$15 -> 22500 | O34: =SUM(I34:N34) -> 112537.5 | P34: =V33 -> 14100 | Q34: 0 | R34: =X33 -> 7200 | S34: =Y33 -> 12000 | T34: =Z33 -> 0 | U34: =AB33 -> 33300 | V34: =P34+H34 -> 15862.5 | W34: 0 | X34: =R34+D34 -> 8100 | Y34: =S34+E34 -> 13500 | Z34: =T34+F34 -> 0 | AB34: =SUM(V34:AA34) -> 37462.5
A35: =A34+1 -> 2034 | B35: =IF(A35=$B$13+$D$16,($B$16*$B$9/$D$16)*(1-$B$14),IF(A35<$B$13+$D$16,$B$16*$B$9/$D$16,0)) -> 1200 | C35: =IF(A35=$B$13+$D$17,($B$17*$B$9/$D$17)*(1-$B$14),IF(A35<$B$13+$D$17,$B$17*$B$9/$D$17,0)) -> 562.5 | D35: =IF(A35=$B$13+$D$18,($B$18*$B$9/$D$18)*(1-$B$14),IF(A35<$B$13+$D$18,$B$18*$B$9/$D$18,0)) -> 900 | E35: =IF(A35=$B$13+$D$19,($B$19*$B$9/$D$19)*(1-$B$14),IF(A35<$B$13+$D$19,$B$19*$B$9/$D$19,0)) -> 1500 | F35: =IF(A35=$B$13+$D$20,($B$20/$D$20)*(1-$B$14),IF(A35<$B$13+$D$20,$B$20/$D$20,0)) -> 0 | G35: =SUM(B35:F35) -> 4162.5 | H35: =B35+C35 -> 1762.5 | I35: =$B$9*($B$16+$B$17)-V35 -> 64875 | J35: =$B$9*($B$18)-X35 -> 13500 | K35: =$B$9*($B$19)-Y35 -> 7500 | L35: =$B$20-Z35+AJ35 -> 0 | N35: =$B$9*$B$15 -> 22500 | O35: =SUM(I35:N35) -> 108375 | P35: =V34 -> 15862.5 | Q35: 0 | R35: =X34 -> 8100 | S35: =Y34 -> 13500 | T35: =Z34 -> 0 | U35: =AB34 -> 37462.5 | V35: =P35+H35 -> 17625 | W35: 0 | X35: =R35+D35 -> 9000 | Y35: =S35+E35 -> 15000 | Z35: =T35+F35 -> 0 | AB35: =SUM(V35:AA35) -> 41625
A36: =A35+1 -> 2035 | B36: =IF(A36=$B$13+$D$16,($B$16*$B$9/$D$16)*(1-$B$14),IF(A36<$B$13+$D$16,$B$16*$B$9/$D$16,0)) -> 1200 | C36: =IF(A36=$B$13+$D$17,($B$17*$B$9/$D$17)*(1-$B$14),IF(A36<$B$13+$D$17,$B$17*$B$9/$D$17,0)) -> 562.5 | D36: =IF(A36=$B$13+$D$18,($B$18*$B$9/$D$18)*(1-$B$14),IF(A36<$B$13+$D$18,$B$18*$B$9/$D$18,0)) -> 900 | E36: =IF(A36=$B$13+$D$19,($B$19*$B$9/$D$19)*(1-$B$14),IF(A36<$B$13+$D$19,$B$19*$B$9/$D$19,0)) -> 1500 | F36: =IF(A36=$B$13+$D$20,($B$20/$D$20)*(1-$B$14),IF(A36<$B$13+$D$20,$B$20/$D$20,0)) -> 0 | G36: =SUM(B36:F36) -> 4162.5 | H36: =B36+C36 -> 1762.5 | I36: =$B$9*($B$16+$B$17)-V36 -> 63112.5 | J36: =$B$9*($B$18)-X36 -> 12600 | K36: =$B$9*($B$19)-Y36 -> 6000 | L36: =$B$20-Z36+AJ36 -> 0 | N36: =$B$9*$B$15 -> 22500 | O36: =SUM(I36:N36) -> 104212.5 | P36: =V35 -> 17625 | Q36: 0 | R36: =X35 -> 9000 | S36: =Y35 -> 15000 | T36: =Z35 -> 0 | U36: =AB35 -> 41625 | V36: =P36+H36 -> 19387.5 | W36: 0 | X36: =R36+D36 -> 9900 | Y36: =S36+E36 -> 16500 | Z36: =T36+F36 -> 0 | AB36: =SUM(V36:AA36) -> 45787.5
A37: =A36+1 -> 2036 | B37: =IF(A37=$B$13+$D$16,($B$16*$B$9/$D$16)*(1-$B$14),IF(A37<$B$13+$D$16,$B$16*$B$9/$D$16,0)) -> 1200 | C37: =IF(A37=$B$13+$D$17,($B$17*$B$9/$D$17)*(1-$B$14),IF(A37<$B$13+$D$17,$B$17*$B$9/$D$17,0)) -> 562.5 | D37: =IF(A37=$B$13+$D$18,($B$18*$B$9/$D$18)*(1-$B$14),IF(A37<$B$13+$D$18,$B$18*$B$9/$D$18,0)) -> 900 | E37: =IF(A37=$B$13+$D$19,($B$19*$B$9/$D$19)*(1-$B$14),IF(A37<$B$13+$D$19,$B$19*$B$9/$D$19,0)) -> 1500 | F37: =IF(A37=$B$13+$D$20,($B$20/$D$20)*(1-$B$14),IF(A37<$B$13+$D$20,$B$20/$D$20,0)) -> 0 | G37: =SUM(B37:F37) -> 4162.5 | H37: =B37+C37 -> 1762.5 | I37: =$B$9*($B$16+$B$17)-V37 -> 61350 | J37: =$B$9*($B$18)-X37 -> 11700 | K37: =$B$9*($B$19)-Y37 -> 4500 | L37: =$B$20-Z37+AJ37 -> 0 | N37: =$B$9*$B$15 -> 22500 | O37: =SUM(I37:N37) -> 100050 | P37: =V36 -> 19387.5 | Q37: 0 | R37: =X36 -> 9900 | S37: =Y36 -> 16500 | T37: =Z36 -> 0 | U37: =AB36 -> 45787.5 | V37: =P37+H37 -> 21150 | W37: 0 | X37: =R37+D37 -> 10800 | Y37: =S37+E37 -> 18000 | Z37: =T37+F37 -> 0 | AB37: =SUM(V37:AA37) -> 49950
A38: =A37+1 -> 2037 | B38: =IF(A38=$B$13+$D$16,($B$16*$B$9/$D$16)*(1-$B$14),IF(A38<$B$13+$D$16,$B$16*$B$9/$D$16,0)) -> 1200 | C38: =IF(A38=$B$13+$D$17,($B$17*$B$9/$D$17)*(1-$B$14),IF(A38<$B$13+$D$17,$B$17*$B$9/$D$17,0)) -> 562.5 | D38: =IF(A38=$B$13+$D$18,($B$18*$B$9/$D$18)*(1-$B$14),IF(A38<$B$13+$D$18,$B$18*$B$9/$D$18,0)) -> 900 | E38: =IF(A38=$B$13+$D$19,($B$19*$B$9/$D$19)*(1-$B$14),IF(A38<$B$13+$D$19,$B$19*$B$9/$D$19,0)) -> 1500 | F38: =IF(A38=$B$13+$D$20,($B$20/$D$20)*(1-$B$14),IF(A38<$B$13+$D$20,$B$20/$D$20,0)) -> 0 | G38: =SUM(B38:F38) -> 4162.5 | H38: =B38+C38 -> 1762.5 | I38: =$B$9*($B$16+$B$17)-V38 -> 59587.5 | J38: =$B$9*($B$18)-X38 -> 10800 | K38: =$B$9*($B$19)-Y38 -> 3000 | L38: =$B$20-Z38+AJ38 -> 0 | N38: =$B$9*$B$15 -> 22500 | O38: =SUM(I38:N38) -> 95887.5 | P38: =V37 -> 21150 | Q38: 0 | R38: =X37 -> 10800 | S38: =Y37 -> 18000 | T38: =Z37 -> 0 | U38: =AB37 -> 49950 | V38: =P38+H38 -> 22912.5 | W38: 0 | X38: =R38+D38 -> 11700 | Y38: =S38+E38 -> 19500 | Z38: =T38+F38 -> 0 | AB38: =SUM(V38:AA38) -> 54112.5
A39: =A38+1 -> 2038 | B39: =IF(A39=$B$13+$D$16,($B$16*$B$9/$D$16)*(1-$B$14),IF(A39<$B$13+$D$16,$B$16*$B$9/$D$16,0)) -> 1200 | C39: =IF(A39=$B$13+$D$17,($B$17*$B$9/$D$17)*(1-$B$14),IF(A39<$B$13+$D$17,$B$17*$B$9/$D$17,0)) -> 562.5 | D39: =IF(A39=$B$13+$D$18,($B$18*$B$9/$D$18)*(1-$B$14),IF(A39<$B$13+$D$18,$B$18*$B$9/$D$18,0)) -> 900 | E39: =IF(A39=$B$13+$D$19,($B$19*$B$9/$D$19)*(1-$B$14),IF(A39<$B$13+$D$19,$B$19*$B$9/$D$19,0)) -> 1500 | F39: =IF(A39=$B$13+$D$20,($B$20/$D$20)*(1-$B$14),IF(A39<$B$13+$D$20,$B$20/$D$20,0)) -> 0 | G39: =SUM(B39:F39) -> 4162.5 | H39: =B39+C39 -> 1762.5 | I39: =$B$9*($B$16+$B$17)-V39 -> 57825 | J39: =$B$9*($B$18)-X39 -> 9900 | K39: =$B$9*($B$19)-Y39 -> 1500 | L39: =$B$20-Z39+AJ39 -> 0 | N39: =$B$9*$B$15 -> 22500 | O39: =SUM(I39:N39) -> 91725 | P39: =V38 -> 22912.5 | Q39: 0 | R39: =X38 -> 11700 | S39: =Y38 -> 19500 | T39: =Z38 -> 0 | U39: =AB38 -> 54112.5 | V39: =P39+H39 -> 24675 | W39: 0 | X39: =R39+D39 -> 12600 | Y39: =S39+E39 -> 21000 | Z39: =T39+F39 -> 0 | AB39: =SUM(V39:AA39) -> 58275
... A76: =A75+1 -> 2075 | B76: =IF(A76=$B$13+$D$16,($B$16*$B$9/$D$16)*(1-$B$14),IF(A76<$B$13+$D$16,$B$16*$B$9/$D$16,0)) -> 0 | C76: =IF(A76=$B$13+$D$17,($B$17*$B$9/$D$17)*(1-$B$14),IF(A76<$B$13+$D$17,$B$17*$B$9/$D$17,0)) -> 0 | D76: =IF(A76=$B$13+$D$18,($B$18*$B$9/$D$18)*(1-$B$14),IF(A76<$B$13+$D$18,$B$18*$B$9/$D$18,0)) -> 0 | E76: =IF(A76=$B$13+$D$19,($B$19*$B$9/$D$19)*(1-$B$14),IF(A76<$B$13+$D$19,$B$19*$B$9/$D$19,0)) -> 0 | F76: =IF(A76=$B$13+$D$20,($B$20/$D$20)*(1-$B$14),IF(A76<$B$13+$D$20,$B$20/$D$20,0)) -> 0 | G76: =SUM(B76:F76) -> 0 | H76: =B76+C76 -> 0 | I76: =$B$9*($B$16+$B$17)-V76 -> 0 | J76: =$B$9*($B$18)-X76 -> 0 | K76: =$B$9*($B$19)-Y76 -> 0 | L76: =$B$20-Z76+AJ76 -> 0 | N76: =$B$9*$B$15 -> 22500 | O76: =SUM(I76:N76) -> 22500 | P76: =V75 -> 82500 | Q76: 0 | R76: =X75 -> 22500 | S76: =Y75 -> 22500 | T76: =Z75 -> 0 | U76: =AB75 -> 127500 | V76: =P76+H76 -> 82500 | W76: 0 | X76: =R76+D76 -> 22500 | Y76: =S76+E76 -> 22500 | Z76: =T76+F76 -> 0 | AB76: =SUM(V76:AA76) -> 127500
A80: ETAPE 3 : Compte de resultat
A82: Année | B82: =F13 -> 2025 | D82: Année | E82: =F13+1 -> 2026
A83: Dotation aux ammortissements (année en cours) | B83: {=INDIRECT(ADDRESS(H13,7))} -> 4162.5 | D83: Dotation aux ammortissements (année en cours) | E83: {=INDIRECT(ADDRESS(H13+1,7))} -> 4162.5
A84: Loyer | B84: 8000 | D84: Loyer | E84: =8000 -> 8000
A85: Charges | B85: =1200+9000 -> 10200 | D85: Charges | E85: =1200 -> 1200
A86: Taxes | B86: 0 | D86: Taxes | E86: 0
A87: Interets d'emprunts | B87: =3000 -> 3000 | D87: Interets d'emprunts | E87: 3000
A88: Resultat comptable avant dotation aux amortissements | B88: =B84-B85-B86-B87 -> -5200 | D88: Resultat comptable avant dotation aux amortissements | E88: =E84-E85-E86-E87 -> 3800
A89: Déficits reportables (Nouvellement crée) | B89: =IF(B88<0,-B88,0) -> 5200 | D89: Déficits reportables (Nouvellement crée) | E89: =IF(E88<0,-E88,0) -> 0
A90: Resultat comptable après dotation aux amortissements | B90: =B88-B83 -> -9362.5 | D90: Resultat comptable après dotation aux amortissements | E90: =E88-E83 -> -362.5
A91: Amortissement excédentaires (Nouvellement crée) | B91: =MIN(B83 , MAX(0 , B83 - B88)) -> 4162.5 | C91: =max(0-B90-B89) -> 4162.5 | D91: Amortissement excédentaires | E91: =MIN(E83 , MAX(0 , E83 - E88)) -> 362.5
A92: Résultat après imputation des amortissements excédentaires | B92: =B91+B90 -> -5200 | D92: Résultat après imputation des amortissements excédentaires | E92: =E91+E90 -> 0
A93: Amortissement excédentaires ANTERIEURS | B93: 0 | D93: Amortissement excédentaires ANTERIEURS | E93: =B96 -> 4162.5
A94: Amortissement ANTERIEURS imputés | B94: =IF(B90<=0,0,MIN(B90,B93)) -> 0 | D94: Amortissement ANTERIEURS imputés | E94: =IF(E90<=0,0,MIN(E90,E93)) -> 0
A95: Amortissement ANTERIEURS restants | B95: =B93-B94 -> 0 | D95: Amortissement ANTERIEURS restants | E95: =E93-E94 -> 4162.5
A96: Amortissements restants à reporter pour les années ultérieures | B96: =B95+B91 -> 4162.5 | D96: Amortissements restants à reporter pour les années ultérieures | E96: =E95+E91 -> 4525
A97: Résultat après imputation des amortisseùents excédentaires ANTERIEURS | B97: =B92-B94 -> -5200 | D97: Résultat après imputation des amortisseùents excédentaires ANTERIEURS | E97: =E92-E94 -> 0
A98: Déficits ANTERIEURS | B98: 0 | D98: Déficits ANTERIEURS | E98: =B101 -> 5200
A99: Déficits ANTERIEURS imputés | B99: =IF(B97<=0,0,MIN(B97,B98)) -> 0 | D99: Déficits ANTERIEURS imputés | E99: =IF(E97<=0,0,MIN(E97,E98)) -> 0
A100: Déficits ANTERIEURS restants | B100: =B98+B99 -> 0 | D100: Déficits ANTERIEURS restants | E100: =E98+E99 -> 5200
A101: Déficits restants à reportrer pour les années ultérieures | B101: =B100+B89 -> 5200 | D101: Déficits restants à reportrer pour les années ultérieures | E101: =E100+E89 -> 5200
A102: Resultat fiscal après imputation : 1/ amortissements excedentaires de l'année en cours 2/ amortissement excédentaires antérieurs 3/ déficits antérieurs | B102: =MAX(0 , B88 - B83) -> 0 | D102: Resultat fiscal après imputation : 1/ amortissements excedentaires de l'année en cours 2/ amortissement excédentaires antérieurs 3/ déficits antérieurs | E102: =MAX(0 , E8 - E83) -> 0
A103: Disponibilité Antérieurs | B103: 0 | D103: Disponibilité Antérieurs | E103: =B104 -> 0
A104: Disponibilités | B104: =Max(0,B84-B85-B86-B87)+B103 -> 0 | D104: Disponibilités | E104: =Max(0,E84-E85-E86-E87)+E103 -> 3800
A105: ETAPE4 : BILAN (2033-A)
A106: Année | B106: =F13 -> 2025 | I106: Année | J106: =F13+1 -> 2026
B107: ACTIF | C107: BRUT | E107: Amortissement/provisions | G107: Net Exercice N | J107: ACTIF | K107: BRUT | M107: Amortissement/provisions | O107: Net Exercice N
A108: Actif immobilisé | B108: Immobilisation corporelles | C108: "028" | D108: =B4+B5 -> 150000 | E108: "030" | F108: {=INDIRECT(ADDRESS(H13,28))} -> 4162.5 | G108: =D108-F108 -> 145837.5 | I108: Actif immobilisé | J108: Immobilisation corporelles | K108: "028" | L108: =D108 -> 150000 | M108: "030" | N108: {=INDIRECT(ADDRESS(H13+1,28))} -> 8325 | O108: =L108-N108 -> 141675
B109: Immobilisation financière | C109: "040" | D109: 0 | E109: "042" | F109: 0 | G109: 0 | J109: Immobilisation financière | K109: "040" | L109: 0 | M109: "042" | N109: 0 | O109: 0
B110: Total | C110: "044" | D110: =D108+D109 -> 150000 | E110: "048" | F110: =F108+F109 -> 4162.5 | G110: =G108+G109 -> 145837.5 | J110: Total | K110: "044" | L110: =L108+L109 -> 150000 | M110: "048" | N110: =N108+N109 -> 8325 | O110: =O108+O109 -> 141675
A111: Actif Circulant | I111: Actif Circulant
B112: Disponibilités | C112: "084" | D112: =B104 -> 0 | G112: =D112 -> 0 | J112: Disponibilités | K112: "084" | L112: =J104 | O112: =L112
A114: Total | C114: "110" | D114: =D110+D112 -> 150000 | E114: "112" | F114: =F110 -> 4162.5 | G114: =G110+G112 -> 145837.5 | I114: Total | K114: "110" | L114: =L110+L112 -> 150000 | M114: "112" | N114: =N110 -> 8325 | O114: =O110+O112 -> 141675
B115: PASSIF | G115: Net Exercice N | J115: PASSIF | O115: Net Exercice N
B116: Capital social ou individuel | C116: "120" | G116: =G114-G118-G120 -> 67200 | J116: Capital social ou individuel | K116: "120" | O116: =O114-O118-O120 -> 70175
B118: Resultat de l'exercice | C118: "136" | G118: =B90 -> -9362.5 | J118: Resultat de l'exercice | K118: "136" | O118: =J90
B120: Emrpunt et dettes assimilés | C120: "156" | G120: =88000 -> 88000 | J120: Emrpunt et dettes assimilés | K120: "156" | O120: =71500 -> 71500
B121: Total II | C121: "176" | G121: =G120 -> 88000 | J121: Total II | K121: "176" | O121: =O120 -> 71500
B122: Total III | C122: "180" | G122: =SUM(G116:G120) -> 145837.5 | J122: Total III | K122: "180" | O122: =SUM(O116:O120) -> 141675
A125: ETAPE 5 : FORMULAIRES
A128: 2033-B | E128: Equilibre | F128: =IF(((B88 - B83) + C143)=B102,"C'est bon","C'est pas bon") -> C'est pas bon | J128: Equilibre | K128: =IF(((E88 - E83) + I143)=E102,"C'est bon","C'est pas bon") -> C'est bon
B129: =F13 -> 2025 | H129: =F13+1 -> 2026
A130: A- RESULTAT COMPTABLE | G130: A- RESULTAT COMPTABLE
A131: production vendue : services | B131: "218" | C131: =B84 -> 8000 | G131: production vendue : services | H131: "218" | I131: =E84 -> 8000
A132: Total produit d'exploitation | B132: "232" | C132: =C131 -> 8000 | G132: Total produit d'exploitation | H132: "232" | I132: =I131 -> 8000
A133: Autre charges externes | B133: "242" | C133: =B85 -> 10200 | G133: Autre charges externes | H133: "242" | I133: =E85 -> 1200
A134: Impots taxe et versement assimilés | B134: "244" | C134: =B86 -> 0 | G134: Impots taxe et versement assimilés | H134: "244" | I134: =E86 -> 0
A135: Dotations aux amortissements | B135: "254" | C135: =B83 -> 4162.5 | G135: Dotations aux amortissements | H135: "254" | I135: =E83 -> 4162.5
A136: Total charges d'exploitation | B136: "264" | C136: =SUM(C133:C135) -> 14362.5 | G136: Total charges d'exploitation | H136: "264" | I136: =SUM(I133:I135) -> 5362.5
A137: Resultat d'exploitation | B137: "270" | C137: =C132-C136 -> -6362.5 | G137: Resultat d'exploitation | H137: "270" | I137: =I132-I136 -> 2637.5
A138: Charges financières | B138: "294" | C138: =B87 -> 3000 | G138: Charges financières | H138: "294" | I138: =E87 -> 3000
A139: Benefices ou perte | B139: "310" | C139: =B90 -> -9362.5 | G139: Benefices ou perte | H139: "310" | I139: =E90 -> -362.5
A140: B- RESULTAT FISCAL | G140: B- RESULTAT FISCAL
A141: Reporter les benef compables | B141: "312" | C141: =Max(0,C139) -> 0 | D141: "314" | E141: =-MIN(0,C139) -> 9362.5 | G141: Reporter les benef compables | H141: "312" | I141: =Max(0,I139) -> 0 | J141: "314" | K141: =-MIN(0,I139) -> 362.5
A142: Amortissements excedentaires | B142: "318" | C142: =B91 -> 4162.5 | D142: "342" | E142: =IF(B88 > 0 , MIN(B88 , B83) , 0) -> 0 | G142: Amortissements excedentaires | H142: "318" | I142: =E91 -> 362.5 | J142: "342" | K142: =IF(E88 > 0 , MIN(E88 , E83) , 0) -> 3800
A143: En ligne : deduction de l'execice : deduction diverses Papier : creance du au titre du report en arrière du deficit | B143: "350" | C143: =B91 -> 4162.5 | D143: "360" | E143: =IF(B88 < 0 , ABS(B88) , 0) -> 5200 | G143: En ligne : deduction de l'execice : deduction diverses Papier : creance du au titre du report en arrière du deficit | H143: "350" | I143: =E91 -> 362.5 | J143: "360" | K143: =IF(E88 < 0 , ABS(E88) , 0) -> 0
A144: Resultat Fiscal avant imputation | B144: "352" | C144: =IF(B97>0,B97,0) -> 0 | D144: "354" | E144: =IF(B97<0,-B97,0) -> 5200 | G144: Resultat Fiscal avant imputation | H144: "352" | I144: =IF(E97>0,E97,0) -> 0 | J144: "354" | K144: =IF(E97<0,-E97,0) -> 0
A145: Resultat Fiscal apres imputation | B145: "370" | C145: =MAX(0 , B88 - B83) -> 0 | D145: "372" | E145: =IF(B102<0,-B102,0) -> 0 | G145: Resultat Fiscal | H145: "370" | I145: =MAX(0 , E88 - E83) -> 0 | J145: "372" | K145: =IF(E102<0,-E102,0) -> 0
A147: 2033-C
A148: 1- Immobilisations
A150: Année | B150: =F13 -> 2025 | K150: Année | L150: =F13+1 -> 2026
B152: Valeur brut des immo en début d'exercice | D152: Augmentation | F152: Diminution | H152: Valeur brute des immo à la fin de l'exercice | L152: Valeur brut des immo en début d'exercice | N152: Augmentation | P152: Diminution | R152: Valeur brute des immo à la fin de l'exercice
A153: Terrains | B153: "420" | C153: 0 | D153: "422" | E153: =IF(F13=B13,B9*B15,0) -> 22500 | F153: "424" | G153: 0 | H153: "426" | I153: =C153+E153+G153 -> 22500 | K153: Terrains | L153: "420" | M153: =I153 -> 22500 | N153: "422" | O153: 0 | P153: "424" | Q153: 0 | R153: "426" | S153: =M153+O153+Q153 -> 22500
...

Sheet LIASSES FISCALES
A1: Etape 1 prix de départ : | D1: Espace Pro : impot gouv : Déclarer : Résultat
A4: Prix d'achat | B4: 150000
A5: Frais de notaire | B5: =8000 -> 8000
A6: frais d'agence | B6: =0 -> 0
A7: Mobilier | B7: =0 -> 0
A8: Travaux à amortir | B8: =0 -> 0
A9: Base amortissable | B9: =IF(B4>0,SUM(B4:B6),IF(E4>0,E4,0)) -> 158000
A11: Etape 2 : Décomposition et amortissement
A12: Date de début d'activité | B12: 45658
A13: Année de début d'activité | B13: =YEAR(B12) -> 2025 | E13: Année d'exercice | F13: =2025 -> 2025 | H13: =F13-B13+26 -> 26
A14: Prorata | B14: =YEARFRAC(B12,DATE(YEAR(B12)+1,1,1),4) -> 1 | AD14: Travaux/Mobilier | AE14: Montant | AF14: Date debut | AG14: Nbr année amortissement | AH14: Prorata première année
A15: Terrain | B15: =15% -> 0.15 | AD15: Travaux/Mobilier 1 | AE15: 0 | AF15: 45809 | AG15: 10 | AH15: =YEARFRAC(AF15,DATE(YEAR(AF15)+1,1,1),4) -> 0.58333333
A16: Structure (Gros oeuvre) | B16: =40% -> 0.4 | C16: du total sur | D16: 50 | E16: ans | AD16: Travaux/Mobilier 2 | AE16: 0 | AF16: 46174 | AG16: 10 | AH16: =YEARFRAC(AF16,DATE(YEAR(AF16)+1,1,1),4) -> 0.58333333
A17: Façade, étanchieté | B17: =15% -> 0.15 | C17: du total sur | D17: 40 | E17: ans | AD17: Travaux/Mobilier 3 | AE17: 0 | AF17: 46539 | AG17: 10 | AH17: =YEARFRAC(AF17,DATE(YEAR(AF17)+1,1,1),4) -> 0.58333333
A18: IGT, Equipement | B18: =15% -> 0.15 | C18: du total sur | D18: 25 | E18: ans | AD18: Travaux/Mobilier 4 | AE18: 0 | AF18: 46905 | AG18: 10 | AH18: =YEARFRAC(AF18,DATE(YEAR(AF18)+1,1,1),4) -> 0.58333333
A19: Agencements (cloisons, chapes, platerie, revetement, plomberie, cablage) | B19: =15% -> 0.15 | C19: du total sur | D19: 15 | E19: ans | AD19: Travaux/Mobilier 5 | AE19: 0 | AF19: 47270 | AG19: 10 | AH19: =YEARFRAC(AF19,DATE(YEAR(AF19)+1,1,1),4) -> 0.58333333
A20: Mobilier+travaux avant 1ere location | B20: =B7+B8 -> 0 | D20: 10 | E20: ans | AD20: Travaux/Mobilier 6 | AE20: 0 | AF20: 47635 | AG20: 10 | AH20: =YEARFRAC(AF20,DATE(YEAR(AF20)+1,1,1),4) -> 0.58333333
A21: Frais de notaire | B21: =B5 -> 8000 | D21: 0 | AD21: Travaux/Mobilier 7 | AE21: 0 | AF21: 48000 | AG21: 10 | AH21: =YEARFRAC(AF21,DATE(YEAR(AF21)+1,1,1),4) -> 0.58333333
A22: Frais d'agence | B22: =B6 -> 0 | D22: 0 | AD22: Travaux/Mobilier 8 | AE22: 0 | AF22: 48000 | AG22: 10 | AH22: =YEARFRAC(AF22,DATE(YEAR(AF22)+1,1,1),4) -> 0.58333333
AD23: Travaux/Mobilier 9 | AE23: 0 | AF23: 48000 | AG23: 10 | AH23: =YEARFRAC(AF23,DATE(YEAR(AF23)+1,1,1),4) -> 0.58333333
C24: Augmentation Amortissement (dotations) | K24: Immobilisations net | Q24: Ammortissement début d'excercice | W24: Ammortissement fin exercice | AD24: Travaux/Mobilier 10 | AE24: 0 | AF24: 48000 | AG24: 10 | AH24: =YEARFRAC(AF24,DATE(YEAR(AF24)+1,1,1),4) -> 0.58333333
A25: Année | B25: Structure | C25: Façade | D25: Equipement | E25: Agencement | F25: Autres immobilisations corporelles | G25: Total Ammortissement | H25: Construction | I25: Construction | J25: Immo equipement | K25: Immo agencement | L25: Autres immobilisations corporelles | N25: Terrain | O25: Total | P25: Construction | Q25: Terrain | R25: Equipement | S25: Agencement | T25: Autres immobilisations corporelles | U25: Total | V25: Construction | W25: Terrain | X25: Equipement | Y25: Agencement | Z25: Autres immobilisations corporelles | AB25: Total
A26: 2025 | B26: =IF(A26<$B$13+$D$16,$B$16*$B$9/$D$16,0)*B14 -> 1264 | C26: =IF(A26<$B$13+$D17,$B$17*$B$9/$D$17,0)*B14 -> 592.5 | D26: =IF(A26<$B$13+$D18,$B$18*$B$9/$D$18,0)*B14 -> 948 | E26: =IF(A26<$B$13+$D$19,$B$19*$B$9/$D$19,0)*B14 -> 1580 | F26: =(IF(A26<$B$13+$D$20,$B$20/$D$20,0)*B14) -> 0 | G26: =SUM(B26:F26) -> 4384.5 | H26: =B26+C26 -> 1856.5 | I26: =$B$9*($B$16+$B$17)-V26 -> 85043.5 | J26: =$B$9*($B$18)-X26 -> 22752 | K26: =$B$9*($B$19)-Y26 -> 22120 | L26: =$B$20-Z26+AJ26 -> 0 | N26: =$B$9*$B$15 -> 23700 | O26: =SUM(I26:N26) -> 153615.5 | P26: 0 | Q26: 0 | R26: 0 | S26: 0 | T26: 0 | U26: 0 | V26: =P26+H26 -> 1856.5 | W26: 0 | X26: =R26+D26 -> 948 | Y26: =S26+E26 -> 1580 | Z26: =T26+F26 -> 0 | AB26: =SUM(V26:AA26) -> 4384.5
A27: 2026 | B27: =IF(A27=$B$13+$D$16,($B$16*$B$9/$D$16)*(1-$B$14),IF(A27<$B$13+$D$16,$B$16*$B$9/$D$16,0)) -> 1264 | C27: =IF(A27=$B$13+$D$17,($B$17*$B$9/$D$17)*(1-$B$14),IF(A27<$B$13+$D$17,$B$17*$B$9/$D$17,0)) -> 592.5 | D27: =IF(A27=$B$13+$D$18,($B$18*$B$9/$D$18)*(1-$B$14),IF(A27<$B$13+$D$18,$B$18*$B$9/$D$18,0)) -> 948 | E27: =IF(A27=$B$13+$D$19,($B$19*$B$9/$D$19)*(1-$B$14),IF(A27<$B$13+$D$19,$B$19*$B$9/$D$19,0)) -> 1580 | F27: =IF(A27=$B$13+$D$20,($B$20/$D$20)*(1-$B$14),IF(A27<$B$13+$D$20,$B$20/$D$20,0)) -> 0 | G27: =SUM(B27:F27) -> 4384.5 | H27: =B27+C27 -> 1856.5 | I27: =$B$9*($B$16+$B$17)-V27 -> 83187 | J27: =$B$9*($B$18)-X27 -> 21804 | K27: =$B$9*($B$19)-Y27 -> 20540 | L27: =$B$20-Z27+AJ27 -> 0 | N27: =$B$9*$B$15 -> 23700 | O27: =SUM(I27:N27) -> 149231 | P27: =V26 -> 1856.5 | Q27: 0 | R27: =X26 -> 948 | S27: =Y26 -> 1580 | T27: =Z26 -> 0 | U27: =AB26 -> 4384.5 | V27: =P27+H27 -> 3713 | W27: 0 | X27: =R27+D27 -> 1896 | Y27: =S27+E27 -> 3160 | Z27: =T27+F27 -> 0 | AB27: =SUM(V27:AA27) -> 8769
A28: =A27+1 -> 2027 | B28: =IF(A28=$B$13+$D$16,($B$16*$B$9/$D$16)*(1-$B$14),IF(A28<$B$13+$D$16,$B$16*$B$9/$D$16,0)) -> 1264 | C28: =IF(A28=$B$13+$D$17,($B$17*$B$9/$D$17)*(1-$B$14),IF(A28<$B$13+$D$17,$B$17*$B$9/$D$17,0)) -> 592.5 | D28: =IF(A28=$B$13+$D$18,($B$18*$B$9/$D$18)*(1-$B$14),IF(A28<$B$13+$D$18,$B$18*$B$9/$D$18,0)) -> 948 | E28: =IF(A28=$B$13+$D$19,($B$19*$B$9/$D$19)*(1-$B$14),IF(A28<$B$13+$D$19,$B$19*$B$9/$D$19,0)) -> 1580 | F28: =IF(A28=$B$13+$D$20,($B$20/$D$20)*(1-$B$14),IF(A28<$B$13+$D$20,$B$20/$D$20,0)) -> 0 | G28: =SUM(B28:F28) -> 4384.5 | H28: =B28+C28 -> 1856.5 | I28: =$B$9*($B$16+$B$17)-V28 -> 81330.5 | J28: =$B$9*($B$18)-X28 -> 20856 | K28: =$B$9*($B$19)-Y28 -> 18960 | L28: =$B$20-Z28+AJ28 -> 0 | N28: =$B$9*$B$15 -> 23700 | O28: =SUM(I28:N28) -> 144846.5 | P28: =V27 -> 3713 | Q28: 0 | R28: =X27 -> 1896 | S28: =Y27 -> 3160 | T28: =Z27 -> 0 | U28: =AB27 -> 8769 | V28: =P28+H28 -> 5569.5 | W28: 0 | X28: =R28+D28 -> 2844 | Y28: =S28+E28 -> 4740 | Z28: =T28+F28 -> 0 | AB28: =SUM(V28:AA28) -> 13153.5
A29: =A28+1 -> 2028 | B29: =IF(A29=$B$13+$D$16,($B$16*$B$9/$D$16)*(1-$B$14),IF(A29<$B$13+$D$16,$B$16*$B$9/$D$16,0)) -> 1264 | C29: =IF(A29=$B$13+$D$17,($B$17*$B$9/$D$17)*(1-$B$14),IF(A29<$B$13+$D$17,$B$17*$B$9/$D$17,0)) -> 592.5 | D29: =IF(A29=$B$13+$D$18,($B$18*$B$9/$D$18)*(1-$B$14),IF(A29<$B$13+$D$18,$B$18*$B$9/$D$18,0)) -> 948 | E29: =IF(A29=$B$13+$D$19,($B$19*$B$9/$D$19)*(1-$B$14),IF(A29<$B$13+$D$19,$B$19*$B$9/$D$19,0)) -> 1580 | F29: =IF(A29=$B$13+$D$20,($B$20/$D$20)*(1-$B$14),IF(A29<$B$13+$D$20,$B$20/$D$20,0)) -> 0 | G29: =SUM(B29:F29) -> 4384.5 | H29: =B29+C29 -> 1856.5 | I29: =$B$9*($B$16+$B$17)-V29 -> 79474 | J29: =$B$9*($B$18)-X29 -> 19908 | K29: =$B$9*($B$19)-Y29 -> 17380 | L29: =$B$20-Z29+AJ29 -> 0 | N29: =$B$9*$B$15 -> 23700 | O29: =SUM(I29:N29) -> 140462 | P29: =V28 -> 5569.5 | Q29: 0 | R29: =X28 -> 2844 | S29: =Y28 -> 4740 | T29: =Z28 -> 0 | U29: =AB28 -> 13153.5 | V29: =P29+H29 -> 7426 | W29: 0 | X29: =R29+D29 -> 3792 | Y29: =S29+E29 -> 6320 | Z29: =T29+F29 -> 0 | AB29: =SUM(V29:AA29) -> 17538
A30: =A29+1 -> 2029 | B30: =IF(A30=$B$13+$D$16,($B$16*$B$9/$D$16)*(1-$B$14),IF(A30<$B$13+$D$16,$B$16*$B$9/$D$16,0)) -> 1264 | C30: =IF(A30=$B$13+$D$17,($B$17*$B$9/$D$17)*(1-$B$14),IF(A30<$B$13+$D$17,$B$17*$B$9/$D$17,0)) -> 592.5 | D30: =IF(A30=$B$13+$D$18,($B$18*$B$9/$D$18)*(1-$B$14),IF(A30<$B$13+$D$18,$B$18*$B$9/$D$18,0)) -> 948 | E30: =IF(A30=$B$13+$D$19,($B$19*$B$9/$D$19)*(1-$B$14),IF(A30<$B$13+$D$19,$B$19*$B$9/$D$19,0)) -> 1580 | F30: =IF(A30=$B$13+$D$20,($B$20/$D$20)*(1-$B$14),IF(A30<$B$13+$D$20,$B$20/$D$20,0)) -> 0 | G30: =SUM(B30:F30) -> 4384.5 | H30: =B30+C30 -> 1856.5 | I30: =$B$9*($B$16+$B$17)-V30 -> 77617.5 | J30: =$B$9*($B$18)-X30 -> 18960 | K30: =$B$9*($B$19)-Y30 -> 15800 | L30: =$B$20-Z30+AJ30 -> 0 | N30: =$B$9*$B$15 -> 23700 | O30: =SUM(I30:N30) -> 136077.5 | P30: =V29 -> 7426 | Q30: 0 | R30: =X29 -> 3792 | S30: =Y29 -> 6320 | T30: =Z29 -> 0 | U30: =AB29 -> 17538 | V30: =P30+H30 -> 9282.5 | W30: 0 | X30: =R30+D30 -> 4740 | Y30: =S30+E30 -> 7900 | Z30: =T30+F30 -> 0 | AB30: =SUM(V30:AA30) -> 21922.5
A31: =A30+1 -> 2030 | B31: =IF(A31=$B$13+$D$16,($B$16*$B$9/$D$16)*(1-$B$14),IF(A31<$B$13+$D$16,$B$16*$B$9/$D$16,0)) -> 1264 | C31: =IF(A31=$B$13+$D$17,($B$17*$B$9/$D$17)*(1-$B$14),IF(A31<$B$13+$D$17,$B$17*$B$9/$D$17,0)) -> 592.5 | D31: =IF(A31=$B$13+$D$18,($B$18*$B$9/$D$18)*(1-$B$14),IF(A31<$B$13+$D$18,$B$18*$B$9/$D$18,0)) -> 948 | E31: =IF(A31=$B$13+$D$19,($B$19*$B$9/$D$19)*(1-$B$14),IF(A31<$B$13+$D$19,$B$19*$B$9/$D$19,0)) -> 1580 | F31: =IF(A31=$B$13+$D$20,($B$20/$D$20)*(1-$B$14),IF(A31<$B$13+$D$20,$B$20/$D$20,0)) -> 0 | G31: =SUM(B31:F31) -> 4384.5 | H31: =B31+C31 -> 1856.5 | I31: =$B$9*($B$16+$B$17)-V31 -> 75761 | J31: =$B$9*($B$18)-X31 -> 18012 | K31: =$B$9*($B$19)-Y31 -> 14220 | L31: =$B$20-Z31+AJ31 -> 0 | N31: =$B$9*$B$15 -> 23700 | O31: =SUM(I31:N31) -> 131693 | P31: =V30 -> 9282.5 | Q31: 0 | R31: =X30 -> 4740 | S31: =Y30 -> 7900 | T31: =Z30 -> 0 | U31: =AB30 -> 21922.5 | V31: =P31+H31 -> 11139 | W31: 0 | X31: =R31+D31 -> 5688 | Y31: =S31+E31 -> 9480 | Z31: =T31+F31 -> 0 | AB31: =SUM(V31:AA31) -> 26307
A32: =A31+1 -> 2031 | B32: =IF(A32=$B$13+$D$16,($B$16*$B$9/$D$16)*(1-$B$14),IF(A32<$B$13+$D$16,$B$16*$B$9/$D$16,0)) -> 1264 | C32: =IF(A32=$B$13+$D$17,($B$17*$B$9/$D$17)*(1-$B$14),IF(A32<$B$13+$D$17,$B$17*$B$9/$D$17,0)) -> 592.5 | D32: =IF(A32=$B$13+$D$18,($B$18*$B$9/$D$18)*(1-$B$14),IF(A32<$B$13+$D$18,$B$18*$B$9/$D$18,0)) -> 948 | E32: =IF(A32=$B$13+$D$19,($B$19*$B$9/$D$19)*(1-$B$14),IF(A32<$B$13+$D$19,$B$19*$B$9/$D$19,0)) -> 1580 | F32: =IF(A32=$B$13+$D$20,($B$20/$D$20)*(1-$B$14),IF(A32<$B$13+$D$20,$B$20/$D$20,0)) -> 0 | G32: =SUM(B32:F32) -> 4384.5 | H32: =B32+C32 -> 1856.5 | I32: =$B$9*($B$16+$B$17)-V32 -> 73904.5 | J32: =$B$9*($B$18)-X32 -> 17064 | K32: =$B$9*($B$19)-Y32 -> 12640 | L32: =$B$20-Z32+AJ32 -> 0 | N32: =$B$9*$B$15 -> 23700 | O32: =SUM(I32:N32) -> 127308.5 | P32: =V31 -> 11139 | Q32: 0 | R32: =X31 -> 5688 | S32: =Y31 -> 9480 | T32: =Z31 -> 0 | U32: =AB31 -> 26307 | V32: =P32+H32 -> 12995.5 | W32: 0 | X32: =R32+D32 -> 6636 | Y32: =S32+E32 -> 11060 | Z32: =T32+F32 -> 0 | AB32: =SUM(V32:AA32) -> 30691.5
A33: =A32+1 -> 2032 | B33: =IF(A33=$B$13+$D$16,($B$16*$B$9/$D$16)*(1-$B$14),IF(A33<$B$13+$D$16,$B$16*$B$9/$D$16,0)) -> 1264 | C33: =IF(A33=$B$13+$D$17,($B$17*$B$9/$D$17)*(1-$B$14),IF(A33<$B$13+$D$17,$B$17*$B$9/$D$17,0)) -> 592.5 | D33: =IF(A33=$B$13+$D$18,($B$18*$B$9/$D$18)*(1-$B$14),IF(A33<$B$13+$D$18,$B$18*$B$9/$D$18,0)) -> 948 | E33: =IF(A33=$B$13+$D$19,($B$19*$B$9/$D$19)*(1-$B$14),IF(A33<$B$13+$D$19,$B$19*$B$9/$D$19,0)) -> 1580 | F33: =IF(A33=$B$13+$D$20,($B$20/$D$20)*(1-$B$14),IF(A33<$B$13+$D$20,$B$20/$D$20,0)) -> 0 | G33: =SUM(B33:F33) -> 4384.5 | H33: =B33+C33 -> 1856.5 | I33: =$B$9*($B$16+$B$17)-V33 -> 72048 | J33: =$B$9*($B$18)-X33 -> 16116 | K33: =$B$9*($B$19)-Y33 -> 11060 | L33: =$B$20-Z33+AJ33 -> 0 | N33: =$B$9*$B$15 -> 23700 | O33: =SUM(I33:N33) -> 122924 | P33: =V32 -> 12995.5 | Q33: 0 | R33: =X32 -> 6636 | S33: =Y32 -> 11060 | T33: =Z32 -> 0 | U33: =AB32 -> 30691.5 | V33: =P33+H33 -> 14852 | W33: 0 | X33: =R33+D33 -> 7584 | Y33: =S33+E33 -> 12640 | Z33: =T33+F33 -> 0 | AB33: =SUM(V33:AA33) -> 35076
A34: =A33+1 -> 2033 | B34: =IF(A34=$B$13+$D$16,($B$16*$B$9/$D$16)*(1-$B$14),IF(A34<$B$13+$D$16,$B$16*$B$9/$D$16,0)) -> 1264 | C34: =IF(A34=$B$13+$D$17,($B$17*$B$9/$D$17)*(1-$B$14),IF(A34<$B$13+$D$17,$B$17*$B$9/$D$17,0)) -> 592.5 | D34: =IF(A34=$B$13+$D$18,($B$18*$B$9/$D$18)*(1-$B$14),IF(A34<$B$13+$D$18,$B$18*$B$9/$D$18,0)) -> 948 | E34: =IF(A34=$B$13+$D$19,($B$19*$B$9/$D$19)*(1-$B$14),IF(A34<$B$13+$D$19,$B$19*$B$9/$D$19,0)) -> 1580 | F34: =IF(A34=$B$13+$D$20,($B$20/$D$20)*(1-$B$14),IF(A34<$B$13+$D$20,$B$20/$D$20,0)) -> 0 | G34: =SUM(B34:F34) -> 4384.5 | H34: =B34+C34 -> 1856.5 | I34: =$B$9*($B$16+$B$17)-V34 -> 70191.5 | J34: =$B$9*($B$18)-X34 -> 15168 | K34: =$B$9*($B$19)-Y34 -> 9480 | L34: =$B$20-Z34+AJ34 -> 0 | N34: =$B$9*$B$15 -> 23700 | O34: =SUM(I34:N34) -> 118539.5 | P34: =V33 -> 14852 | Q34: 0 | R34: =X33 -> 7584 | S34: =Y33 -> 12640 | T34: =Z33 -> 0 | U34: =AB33 -> 35076 | V34: =P34+H34 -> 16708.5 | W34: 0 | X34: =R34+D34 -> 8532 | Y34: =S34+E34 -> 14220 | Z34: =T34+F34 -> 0 | AB34: =SUM(V34:AA34) -> 39460.5
A35: =A34+1 -> 2034 | B35: =IF(A35=$B$13+$D$16,($B$16*$B$9/$D$16)*(1-$B$14),IF(A35<$B$13+$D$16,$B$16*$B$9/$D$16,0)) -> 1264 | C35: =IF(A35=$B$13+$D$17,($B$17*$B$9/$D$17)*(1-$B$14),IF(A35<$B$13+$D$17,$B$17*$B$9/$D$17,0)) -> 592.5 | D35: =IF(A35=$B$13+$D$18,($B$18*$B$9/$D$18)*(1-$B$14),IF(A35<$B$13+$D$18,$B$18*$B$9/$D$18,0)) -> 948 | E35: =IF(A35=$B$13+$D$19,($B$19*$B$9/$D$19)*(1-$B$14),IF(A35<$B$13+$D$19,$B$19*$B$9/$D$19,0)) -> 1580 | F35: =IF(A35=$B$13+$D$20,($B$20/$D$20)*(1-$B$14),IF(A35<$B$13+$D$20,$B$20/$D$20,0)) -> 0 | G35: =SUM(B35:F35) -> 4384.5 | H35: =B35+C35 -> 1856.5 | I35: =$B$9*($B$16+$B$17)-V35 -> 68335 | J35: =$B$9*($B$18)-X35 -> 14220 | K35: =$B$9*($B$19)-Y35 -> 7900 | L35: =$B$20-Z35+AJ35 -> 0 | N35: =$B$9*$B$15 -> 23700 | O35: =SUM(I35:N35) -> 114155 | P35: =V34 -> 16708.5 | Q35: 0 | R35: =X34 -> 8532 | S35: =Y34 -> 14220 | T35: =Z34 -> 0 | U35: =AB34 -> 39460.5 | V35: =P35+H35 -> 18565 | W35: 0 | X35: =R35+D35 -> 9480 | Y35: =S35+E35 -> 15800 | Z35: =T35+F35 -> 0 | AB35: =SUM(V35:AA35) -> 43845
A36: =A35+1 -> 2035 | B36: =IF(A36=$B$13+$D$16,($B$16*$B$9/$D$16)*(1-$B$14),IF(A36<$B$13+$D$16,$B$16*$B$9/$D$16,0)) -> 1264 | C36: =IF(A36=$B$13+$D$17,($B$17*$B$9/$D$17)*(1-$B$14),IF(A36<$B$13+$D$17,$B$17*$B$9/$D$17,0)) -> 592.5 | D36: =IF(A36=$B$13+$D$18,($B$18*$B$9/$D$18)*(1-$B$14),IF(A36<$B$13+$D$18,$B$18*$B$9/$D$18,0)) -> 948 | E36: =IF(A36=$B$13+$D$19,($B$19*$B$9/$D$19)*(1-$B$14),IF(A36<$B$13+$D$19,$B$19*$B$9/$D$19,0)) -> 1580 | F36: =IF(A36=$B$13+$D$20,($B$20/$D$20)*(1-$B$14),IF(A36<$B$13+$D$20,$B$20/$D$20,0)) -> 0 | G36: =SUM(B36:F36) -> 4384.5 | H36: =B36+C36 -> 1856.5 | I36: =$B$9*($B$16+$B$17)-V36 -> 66478.5 | J36: =$B$9*($B$18)-X36 -> 13272 | K36: =$B$9*($B$19)-Y36 -> 6320 | L36: =$B$20-Z36+AJ36 -> 0 | N36: =$B$9*$B$15 -> 23700 | O36: =SUM(I36:N36) -> 109770.5 | P36: =V35 -> 18565 | Q36: 0 | R36: =X35 -> 9480 | S36: =Y35 -> 15800 | T36: =Z35 -> 0 | U36: =AB35 -> 43845 | V36: =P36+H36 -> 20421.5 | W36: 0 | X36: =R36+D36 -> 10428 | Y36: =S36+E36 -> 17380 | Z36: =T36+F36 -> 0 | AB36: =SUM(V36:AA36) -> 48229.5
A37: =A36+1 -> 2036 | B37: =IF(A37=$B$13+$D$16,($B$16*$B$9/$D$16)*(1-$B$14),IF(A37<$B$13+$D$16,$B$16*$B$9/$D$16,0)) -> 1264 | C37: =IF(A37=$B$13+$D$17,($B$17*$B$9/$D$17)*(1-$B$14),IF(A37<$B$13+$D$17,$B$17*$B$9/$D$17,0)) -> 592.5 | D37: =IF(A37=$B$13+$D$18,($B$18*$B$9/$D$18)*(1-$B$14),IF(A37<$B$13+$D$18,$B$18*$B$9/$D$18,0)) -> 948 | E37: =IF(A37=$B$13+$D$19,($B$19*$B$9/$D$19)*(1-$B$14),IF(A37<$B$13+$D$19,$B$19*$B$9/$D$19,0)) -> 1580 | F37: =IF(A37=$B$13+$D$20,($B$20/$D$20)*(1-$B$14),IF(A37<$B$13+$D$20,$B$20/$D$20,0)) -> 0 | G37: =SUM(B37:F37) -> 4384.5 | H37: =B37+C37 -> 1856.5 | I37: =$B$9*($B$16+$B$17)-V37 -> 64622 | J37: =$B$9*($B$18)-X37 -> 12324 | K37: =$B$9*($B$19)-Y37 -> 4740 | L37: =$B$20-Z37+AJ37 -> 0 | N37: =$B$9*$B$15 -> 23700 | O37: =SUM(I37:N37) -> 105386 | P37: =V36 -> 20421.5 | Q37: 0 | R37: =X36 -> 10428 | S37: =Y36 -> 17380 | T37: =Z36 -> 0 | U37: =AB36 -> 48229.5 | V37: =P37+H37 -> 22278 | W37: 0 | X37: =R37+D37 -> 11376 | Y37: =S37+E37 -> 18960 | Z37: =T37+F37 -> 0 | AB37: =SUM(V37:AA37) -> 52614
A38: =A37+1 -> 2037 | B38: =IF(A38=$B$13+$D$16,($B$16*$B$9/$D$16)*(1-$B$14),IF(A38<$B$13+$D$16,$B$16*$B$9/$D$16,0)) -> 1264 | C38: =IF(A38=$B$13+$D$17,($B$17*$B$9/$D$17)*(1-$B$14),IF(A38<$B$13+$D$17,$B$17*$B$9/$D$17,0)) -> 592.5 | D38: =IF(A38=$B$13+$D$18,($B$18*$B$9/$D$18)*(1-$B$14),IF(A38<$B$13+$D$18,$B$18*$B$9/$D$18,0)) -> 948 | E38: =IF(A38=$B$13+$D$19,($B$19*$B$9/$D$19)*(1-$B$14),IF(A38<$B$13+$D$19,$B$19*$B$9/$D$19,0)) -> 1580 | F38: =IF(A38=$B$13+$D$20,($B$20/$D$20)*(1-$B$14),IF(A38<$B$13+$D$20,$B$20/$D$20,0)) -> 0 | G38: =SUM(B38:F38) -> 4384.5 | H38: =B38+C38 -> 1856.5 | I38: =$B$9*($B$16+$B$17)-V38 -> 62765.5 | J38: =$B$9*($B$18)-X38 -> 11376 | K38: =$B$9*($B$19)-Y38 -> 3160 | L38: =$B$20-Z38+AJ38 -> 0 | N38: =$B$9*$B$15 -> 23700 | O38: =SUM(I38:N38) -> 101001.5 | P38: =V37 -> 22278 | Q38: 0 | R38: =X37 -> 11376 | S38: =Y37 -> 18960 | T38: =Z37 -> 0 | U38: =AB37 -> 52614 | V38: =P38+H38 -> 24134.5 | W38: 0 | X38: =R38+D38 -> 12324 | Y38: =S38+E38 -> 20540 | Z38: =T38+F38 -> 0 | AB38: =SUM(V38:AA38) -> 56998.5
A39: =A38+1 -> 2038 | B39: =IF(A39=$B$13+$D$16,($B$16*$B$9/$D$16)*(1-$B$14),IF(A39<$B$13+$D$16,$B$16*$B$9/$D$16,0)) -> 1264 | C39: =IF(A39=$B$13+$D$17,($B$17*$B$9/$D$17)*(1-$B$14),IF(A39<$B$13+$D$17,$B$17*$B$9/$D$17,0)) -> 592.5 | D39: =IF(A39=$B$13+$D$18,($B$18*$B$9/$D$18)*(1-$B$14),IF(A39<$B$13+$D$18,$B$18*$B$9/$D$18,0)) -> 948 | E39: =IF(A39=$B$13+$D$19,($B$19*$B$9/$D$19)*(1-$B$14),IF(A39<$B$13+$D$19,$B$19*$B$9/$D$19,0)) -> 1580 | F39: =IF(A39=$B$13+$D$20,($B$20/$D$20)*(1-$B$14),IF(A39<$B$13+$D$20,$B$20/$D$20,0)) -> 0 | G39: =SUM(B39:F39) -> 4384.5 | H39: =B39+C39 -> 1856.5 | I39: =$B$9*($B$16+$B$17)-V39 -> 60909 | J39: =$B$9*($B$18)-X39 -> 10428 | K39: =$B$9*($B$19)-Y39 -> 1580 | L39: =$B$20-Z39+AJ39 -> 0 | N39: =$B$9*$B$15 -> 23700 | O39: =SUM(I39:N39) -> 96617 | P39: =V38 -> 24134.5 | Q39: 0 | R39: =X38 -> 12324 | S39: =Y38 -> 20540 | T39: =Z38 -> 0 | U39: =AB38 -> 56998.5 | V39: =P39+H39 -> 25991 | W39: 0 | X39: =R39+D39 -> 13272 | Y39: =S39+E39 -> 22120 | Z39: =T39+F39 -> 0 | AB39: =SUM(V39:AA39) -> 61383
... A76: =A75+1 -> 2075 | B76: =IF(A76=$B$13+$D$16,($B$16*$B$9/$D$16)*(1-$B$14),IF(A76<$B$13+$D$16,$B$16*$B$9/$D$16,0)) -> 0 | C76: =IF(A76=$B$13+$D$17,($B$17*$B$9/$D$17)*(1-$B$14),IF(A76<$B$13+$D$17,$B$17*$B$9/$D$17,0)) -> 0 | D76: =IF(A76=$B$13+$D$18,($B$18*$B$9/$D$18)*(1-$B$14),IF(A76<$B$13+$D$18,$B$18*$B$9/$D$18,0)) -> 0 | E76: =IF(A76=$B$13+$D$19,($B$19*$B$9/$D$19)*(1-$B$14),IF(A76<$B$13+$D$19,$B$19*$B$9/$D$19,0)) -> 0 | F76: =IF(A76=$B$13+$D$20,($B$20/$D$20)*(1-$B$14),IF(A76<$B$13+$D$20,$B$20/$D$20,0)) -> 0 | G76: =SUM(B76:F76) -> 0 | H76: =B76+C76 -> 0 | I76: =$B$9*($B$16+$B$17)-V76 -> 0 | J76: =$B$9*($B$18)-X76 -> 0 | K76: =$B$9*($B$19)-Y76 -> 0 | L76: =$B$20-Z76+AJ76 -> 0 | N76: =$B$9*$B$15 -> 23700 | O76: =SUM(I76:N76) -> 23700 | P76: =V75 -> 86900 | Q76: 0 | R76: =X75 -> 23700 | S76: =Y75 -> 23700 | T76: =Z75 -> 0 | U76: =AB75 -> 134300 | V76: =P76+H76 -> 86900 | W76: 0 | X76: =R76+D76 -> 23700 | Y76: =S76+E76 -> 23700 | Z76: =T76+F76 -> 0 | AB76: =SUM(V76:AA76) -> 134300
A80: ETAPE 2 : Compte de resultat
A82: Année | B82: =F13 -> 2025 | D82: Année | E82: =F13+1 -> 2026
A83: Dotation aux ammortissements (année en cours) | B83: {=INDIRECT(ADDRESS(H13,7))} -> 4384.5 | D83: Dotation aux ammortissements (année en cours) | E83: {=INDIRECT(ADDRESS(H13+1,7))} -> 4384.5
A84: Loyer | B84: 8000 | D84: Loyer | E84: =8000 -> 8000
A85: Charges | B85: =1200+9000 -> 10200 | D85: Charges | E85: =1200 -> 1200
A86: Taxes | B86: 2000 | D86: Taxes | E86: 2000
A87: Interets d'emprunts | B87: =3000 -> 3000 | D87: Interets d'emprunts | E87: 3000
A88: Resultat comptable avant dotation aux amortissements | B88: =B84-B85-B86-B87 -> -7200 | D88: Resultat comptable avant dotation aux amortissements | E88: =E84-E85-E86-E87 -> 1800
A89: Déficits reportables (Nouvellement crée) | B89: =IF(B88<0,-B88,0) -> 7200 | D89: Déficits reportables (Nouvellement crée) | E89: =IF(E88<0,-E88,0) -> 0
A90: Resultat comptable après dotation aux amortissements | B90: =B88-B83 -> -11584.5 | D90: Resultat comptable après dotation aux amortissements | E90: =E88-E83 -> -2584.5
A91: Amortissement excédentaires (Nouvellement crée) | B91: =MIN(B83 , MAX(0 , B83 - B88)) -> 4384.5 | C91: =max(0-B90-B89) -> 4384.5 | D91: Amortissement excédentaires | E91: =MIN(E83 , MAX(0 , E83 - E88)) -> 2584.5
A92: Résultat après imputation des amortissements excédentaires | B92: =B91+B90 -> -7200 | D92: Résultat après imputation des amortissements excédentaires | E92: =E91+E90 -> 0
A93: Amortissement excédentaires ANTERIEURS | B93: 0 | D93: Amortissement excédentaires ANTERIEURS | E93: =B96 -> 4384.5
A94: Amortissement ANTERIEURS imputés | B94: =IF(B90<=0,0,MIN(B90,B93)) -> 0 | D94: Amortissement ANTERIEURS imputés | E94: =IF(E90<=0,0,MIN(E90,E93)) -> 0
A95: Amortissement ANTERIEURS restants | B95: =B93-B94 -> 0 | D95: Amortissement ANTERIEURS restants | E95: =E93-E94 -> 4384.5
A96: Amortissements restants à reporter pour les années ultérieures | B96: =B95+B91 -> 4384.5 | D96: Amortissements restants à reporter pour les années ultérieures | E96: =E95+E91 -> 6969
A97: Résultat après imputation des amortisseùents excédentaires ANTERIEURS | B97: =B92-B94 -> -7200 | D97: Résultat après imputation des amortisseùents excédentaires ANTERIEURS | E97: =E92-E94 -> 0
A98: Déficits ANTERIEURS | B98: 0 | D98: Déficits ANTERIEURS | E98: =B101 -> 7200
A99: Déficits ANTERIEURS imputés | B99: =IF(B97<=0,0,MIN(B97,B98)) -> 0 | D99: Déficits ANTERIEURS imputés | E99: =IF(E97<=0,0,MIN(E97,E98)) -> 0
A100: Déficits ANTERIEURS restants | B100: =B98+B99 -> 0 | D100: Déficits ANTERIEURS restants | E100: =E98+E99 -> 7200
A101: Déficits restants à reportrer pour les années ultérieures | B101: =B100+B89 -> 7200 | D101: Déficits restants à reportrer pour les années ultérieures | E101: =E100+E89 -> 7200
A102: Resultat fiscal après imputation : 1/ amortissements excedentaires de l'année en cours 2/ amortissement excédentaires antérieurs 3/ déficits antérieurs | B102: =MAX(0 , B88 - B83) -> 0 | D102: Resultat fiscal après imputation : 1/ amortissements excedentaires de l'année en cours 2/ amortissement excédentaires antérieurs 3/ déficits antérieurs | E102: =MAX(0 , E88 - E83) -> 0
A103: Disponibilité Antérieurs | B103: 0 | D103: Disponibilité Antérieurs | E103: =B104 -> 0
A104: Disponibilités | B104: =Max(0,B84-B85-B86-B87)+B103 -> 0 | D104: Disponibilités | E104: =Max(0,E84-E85-E86-E87)+E103 -> 1800
A107: BILAN (2033-A)
A108: Année | B108: =F13 -> 2025 | I108: Année | J108: =F13+1 -> 2026
B109: ACTIF | C109: BRUT | E109: Amortissement/provisions | G109: Net Exercice N | J109: ACTIF | K109: BRUT | M109: Amortissement/provisions | O109: Net Exercice N
A110: Actif immobilisé | B110: Immobilisation corporelles | C110: "028" | D110: =B4+B5 -> 158000 | E110: "030" | F110: {=INDIRECT(ADDRESS(H13,28))} -> 4384.5 | G110: =D110-F110 -> 153615.5 | I110: Actif immobilisé | J110: Immobilisation corporelles | K110: "028" | L110: =D110 -> 158000 | M110: "030" | N110: {=INDIRECT(ADDRESS(H13+1,28))} -> 8769 | O110: =L110-N110 -> 149231
B111: Immobilisation financière | C111: "040" | D111: 0 | E111: "042" | F111: 0 | G111: 0 | J111: Immobilisation financière | K111: "040" | L111: 0 | M111: "042" | N111: 0 | O111: 0
B112: Total | C112: "044" | D112: =D110+D111 -> 158000 | E112: "048" | F112: =F110+F111 -> 4384.5 | G112: =G110+G111 -> 153615.5 | J112: Total | K112: "044" | L112: =L110+L111 -> 158000 | M112: "048" | N112: =N110+N111 -> 8769 | O112: =O110+O111 -> 149231
A113: Actif Circulant | I113: Actif Circulant
B114: Disponibilités | C114: "084" | D114: =B104 -> 0 | G114: =D114 -> 0 | J114: Disponibilités | K114: "084" | L114: =J104 | O114: =L114
A116: Total | C116: "110" | D116: =D112+D114 -> 158000 | E116: "112" | F116: =F112 -> 4384.5 | G116: =G112+G114 -> 153615.5 | I116: Total | K116: "110" | L116: =L112+L114 -> 158000 | M116: "112" | N116: =N112 -> 8769 | O116: =O112+O114 -> 149231
B117: PASSIF | G117: Net Exercice N | J117: PASSIF | O117: Net Exercice N
B118: Capital social ou individuel | C118: "120" | G118: =G116-G120-G122 -> 77200 | J118: Capital social ou individuel | K118: "120" | O118: =O116-O120-O122 -> 77731
B120: Resultat de l'exercice | C120: "136" | G120: =B90 -> -11584.5 | J120: Resultat de l'exercice | K120: "136" | O120: =J90
B122: Emrpunt et dettes assimilés | C122: "156" | G122: =88000 -> 88000 | J122: Emrpunt et dettes assimilés | K122: "156" | O122: =71500 -> 71500
B123: Total II | C123: "176" | G123: =G122 -> 88000 | J123: Total II | K123: "176" | O123: =O122 -> 71500
B124: Total III | C124: "180" | G124: =SUM(G118:G122) -> 153615.5 | J124: Total III | K124: "180" | O124: =SUM(O118:O122) -> 149231
A127: 2033-B | E127: Equilibre | F127: =IF(((B88 - B83) + C142)=B102,"C'est bon","C'est pas bon") -> C'est pas bon | J127: Equilibre | K127: =IF(((E88 - E83) + I142)=E102,"C'est bon","C'est pas bon") -> C'est bon
B128: =F13 -> 2025 | H128: =F13+1 -> 2026
A129: A- RESULTAT COMPTABLE | G129: A- RESULTAT COMPTABLE
A130: production vendue : services | B130: "218" | C130: =B84 -> 8000 | G130: production vendue : services | H130: "218" | I130: =E84 -> 8000
A131: Total produit d'exploitation | B131: "232" | C131: =C130 -> 8000 | G131: Total produit d'exploitation | H131: "232" | I131: =I130 -> 8000
A132: Autre charges externes | B132: "242" | C132: =B85 -> 10200 | G132: Autre charges externes | H132: "242" | I132: =E85 -> 1200
A133: Impots taxe et versement assimilés | B133: "244" | C133: =B86 -> 2000 | G133: Impots taxe et versement assimilés | H133: "244" | I133: =E86 -> 2000
A134: Dotations aux amortissements | B134: "254" | C134: =B83 -> 4384.5 | G134: Dotations aux amortissements | H134: "254" | I134: =E83 -> 4384.5
A135: Total charges d'exploitation | B135: "264" | C135: =SUM(C132:C134) -> 16584.5 | G135: Total charges d'exploitation | H135: "264" | I135: =SUM(I132:I134) -> 7584.5
A136: Resultat d'exploitation | B136: "270" | C136: =C131-C135 -> -8584.5 | G136: Resultat d'exploitation | H136: "270" | I136: =I131-I135 -> 415.5
A137: Charges financières | B137: "294" | C137: =B87 -> 3000 | G137: Charges financières | H137: "294" | I137: =E87 -> 3000
A138: Benefices ou perte | B138: "310" | C138: =B90 -> -11584.5 | G138: Benefices ou perte | H138: "310" | I138: =E90 -> -2584.5
A139: B- RESULTAT FISCAL | G139: B- RESULTAT FISCAL
A140: Reporter les benef compables | B140: "312" | C140: =Max(0,C138) -> 0 | D140: "314" | E140: =-MIN(0,C138) -> 11584.5 | G140: Reporter les benef compables | H140: "312" | I140: =Max(0,I138) -> 0 | J140: "314" | K140: =-MIN(0,I138) -> 2584.5
A141: Amortissements excedentaires | B141: "318" | C141: =B91 -> 4384.5 | D141: "342" | E141: =IF(B88 > 0 , MIN(B88 , B83) , 0) -> 0 | G141: Amortissements excedentaires | H141: "318" | I141: =E91 -> 2584.5 | J141: "342" | K141: =IF(E88 > 0 , MIN(E88 , E83) , 0) -> 1800
A142: En ligne : deduction de l'execice : deduction diverses Papier : creance du au titre du report en arrière du deficit | B142: "350" | C142: =B91 -> 4384.5 | D142: "360" | E142: =IF(B88 < 0 , ABS(B88) , 0) -> 7200 | G142: En ligne : deduction de l'execice : deduction diverses Papier : creance du au titre du report en arrière du deficit | H142: "350" | I142: =E91 -> 2584.5 | J142: "360" | K142: =IF(E88 < 0 , ABS(E88) , 0) -> 0
A143: Resultat Fiscal avant imputation | B143: "352" | C143: =IF(B97>0,B97,0) -> 0 | D143: "354" | E143: =IF(B97<0,-B97,0) -> 7200 | G143: Resultat Fiscal avant imputation | H143: "352" | I143: =IF(E97>0,E97,0) -> 0 | J143: "354" | K143: =IF(E97<0,-E97,0) -> 0
A144: Resultat Fiscal apres imputation | B144: "370" | C144: =MAX(0 , B88 - B83) -> 0 | D144: "372" | E144: =IF(B102<0,-B102,0) -> 0 | G144: Resultat Fiscal | H144: "370" | I144: =MAX(0 , E88 - E83) -> 0 | J144: "372" | K144: =IF(E102<0,-E102,0) -> 0
A146: 2033-C
A147: 1- Immobilisations
A149: Année | B149: =F13 -> 2025 | K149: Année | L149: =F13+1 -> 2026
B151: Valeur brut des immo en début d'exercice | D151: Augmentation | F151: Diminution | H151: Valeur brute des immo à la fin de l'exercice | L151: Valeur brut des immo en début d'exercice | N151: Augmentation | P151: Diminution | R151: Valeur brute des immo à la fin de l'exercice
A152: Terrains | B152: "420" | C152: 0 | D152: "422" | E152: =IF(F13=B13,B9*B15,0) -> 23700 | F152: "424" | G152: 0 | H152: "426" | I152: =C152+E152+G152 -> 23700 | K152: Terrains | L152: "420" | M152: =I152 -> 23700 | N152: "422" | O152: 0 | P152: "424" | Q152: 0 | R152: "426" | S152: =M152+O152+Q152 -> 23700
A153: Constructions | B153: "430" | C153: 0 | D153: "432" | E153: =IF(F13=B13,B9*(B16+B17),0) -> 86900 | F153: "434" | G153: 0 | H153: "436" | I153: =C153+E153+G153 -> 86900 | K153: Constructions | L153: "430" | M153: =I153 -> 86900 | N153: "432" | O153: 0 | P153: "434" | Q153: 0 | R153: "436" | S153: =M153+O153+Q153 -> 86900
...

Sheet 2031
A1: Cadre C | B1: Col 1 | C1: Col 2
A2: 1 - Resultat fiscal | B2: case 370 | C2: 360
A3: 7-Dont BIC non professionnels | B3: case 370 | C3: 360
A5: Cadre D
A6: Vide
A8: Cadre E
A9: Nom prénom, adresse, SIREN | B9: part du benef 100% | C9: Montant case 370 | D9: 360
A11: Cadre F, G, H
A12: Vide
A14: I- BIC non professionnels
A15: Autres locations non prof | B15: case 370 | C15: 360

Sheet 2042-C-PRO
A1: 1. Identification (page 1)
A3: 2. Le report du résultat (Le plus important)
A4: REVENU INDUS ET COMMERCIAUX NON PROF
A5: - Régime du benefice reel (page 2)
A7: Case 5NA | B7: case 370
A8: Case 5NY | B8: case 360
A9: deficit des années antérieur à noter : case en bas du 5NY | B9: deficit anterieur dispo dans la page de calcul
A11: BA, BIC, BNC à imposer aux prélévements sociaux
A12: Case 5HY | B12: Vide

Sheet rep finale
A1: ID | B1: email | C1: Cases | D1: Montant
A2: 1 | B2: email@email.com | C2: 028 | D2: 1500
A3: 2 | B3: email@email.com | C3: 030 | D3: 400
A4: 3 | B4: email@email.com | C4: 028+030 | D4: 1900
C5: 040
C6: 042
C7: 040+042
C8: 044
C9: 048
C10: 044+048
C11: 084
C12: 110
C13: 112
C14: 110+112
C15: 120
C16: 136
... C99: 870
